{"resolved":{"theme":{"spacing":{"0":"0px","1":"1px","2":"2px","4":"4px","6":"6px","8":"8px","10":"10px","12":"12px","14":"14px","16":"16px","18":"18px","20":"20px","24":"24px","28":"28px","32":"32px","40":"40px","60":"60px","80":"80px"},"screens":{"sm":{"max":"600px"},"lg":{"min":"600px"}},"colors":{"transparent":"transparent","current":"currentColor","blue":{"from":"#8A78FD","to":"#796BFD","light":"#7084ff","DEFAULT":"#796BFD","purple":"#5F75FF"},"black":"#707280","green":"#27C193","white":"#fff","yellow":"#F29C1B","orange":"#FFB020","pink":"#F24822","red":{"light":"#F24822","DEFAULT":"#AF160E","forbidden":"#EC5151"},"gray":{"bg2":"#F5F6FA","bg":"#F5F6FA","divider":"#E5E9EF","comment":"#B4BDCC","content":"#707280","subTitle":"#4B4D59","title":"#13141A","light":"#707880","common":"#666666"},"r":{"blue-default":"var(--r-blue-default, #7084ff)","blue-light1":"var(--r-blue-light1, #eef1ff)","blue-light-1":"var(--r-blue-light-1, #eef1ff)","blue-light2":"var(--r-blue-light2, #dee3fc)","blue-light-2":"var(--r-blue-light-2, #dee3fc)","blue-disable":"var(--r-blue-disable, #dbe0ff)","green-default":"var(--r-green-default, #2abb7f)","green-light":"var(--r-green-light, #d8f2e7)","orange-default":"var(--r-orange-default, #ffb020)","orange-light":"var(--r-orange-light, #fff5e2)","red-default":"var(--r-red-default, #e34935)","red-light":"var(--r-red-light, #fff2f0)","red-dark":"var(--r-red-dark, #ae2a19)","red-light2":"var(--r-red-light2, #efd4d1)","red-light-2":"var(--r-red-light-2, #efd4d1)","neutral-title1":"var(--r-neutral-title1, #192945)","neutral-title-1":"var(--r-neutral-title-1, #192945)","neutral-body":"var(--r-neutral-body, #3e495e)","neutral-foot":"var(--r-neutral-foot, #6a7587)","neutral-line":"var(--r-neutral-line, #d3d8e0)","neutral-bg1":"var(--r-neutral-bg1, #ffffff)","neutral-bg-1":"var(--r-neutral-bg-1, #ffffff)","neutral-bg2":"var(--r-neutral-bg2, #f2f4f7)","neutral-bg-2":"var(--r-neutral-bg-2, #f2f4f7)","neutral-bg3":"var(--r-neutral-bg3, #f7fafc)","neutral-bg-3":"var(--r-neutral-bg-3, #f7fafc)","neutral-card1":"var(--r-neutral-card1, #ffffff)","neutral-card-1":"var(--r-neutral-card-1, #ffffff)","neutral-card2":"var(--r-neutral-card2, #f2f4f7)","neutral-card-2":"var(--r-neutral-card-2, #f2f4f7)","neutral-card3":"var(--r-neutral-card3, #f7fafc)","neutral-card-3":"var(--r-neutral-card-3, #f7fafc)","neutral-title2":"var(--r-neutral-title2, #ffffff)","neutral-title-2":"var(--r-neutral-title-2, #ffffff)","neutral-black":"var(--r-neutral-black, #000000)"},"rabby":{"blue-default":"var(--r-blue-default, #7084ff)","blue-light1":"var(--r-blue-light1, #eef1ff)","blue-light-1":"var(--r-blue-light-1, #eef1ff)","blue-light2":"var(--r-blue-light2, #dee3fc)","blue-light-2":"var(--r-blue-light-2, #dee3fc)","blue-disable":"var(--r-blue-disable, #dbe0ff)","green-default":"var(--r-green-default, #2abb7f)","green-light":"var(--r-green-light, #d8f2e7)","orange-default":"var(--r-orange-default, #ffb020)","orange-light":"var(--r-orange-light, #fff5e2)","red-default":"var(--r-red-default, #e34935)","red-light":"var(--r-red-light, #fff2f0)","red-dark":"var(--r-red-dark, #ae2a19)","red-light2":"var(--r-red-light2, #efd4d1)","red-light-2":"var(--r-red-light-2, #efd4d1)","neutral-title1":"var(--r-neutral-title1, #192945)","neutral-title-1":"var(--r-neutral-title-1, #192945)","neutral-body":"var(--r-neutral-body, #3e495e)","neutral-foot":"var(--r-neutral-foot, #6a7587)","neutral-line":"var(--r-neutral-line, #d3d8e0)","neutral-bg1":"var(--r-neutral-bg1, #ffffff)","neutral-bg-1":"var(--r-neutral-bg-1, #ffffff)","neutral-bg2":"var(--r-neutral-bg2, #f2f4f7)","neutral-bg-2":"var(--r-neutral-bg-2, #f2f4f7)","neutral-bg3":"var(--r-neutral-bg3, #f7fafc)","neutral-bg-3":"var(--r-neutral-bg-3, #f7fafc)","neutral-card1":"var(--r-neutral-card1, #ffffff)","neutral-card-1":"var(--r-neutral-card-1, #ffffff)","neutral-card2":"var(--r-neutral-card2, #f2f4f7)","neutral-card-2":"var(--r-neutral-card-2, #f2f4f7)","neutral-card3":"var(--r-neutral-card3, #f7fafc)","neutral-card-3":"var(--r-neutral-card-3, #f7fafc)","neutral-title2":"var(--r-neutral-title2, #ffffff)","neutral-title-2":"var(--r-neutral-title-2, #ffffff)","neutral-black":"var(--r-neutral-black, #000000)"},"-r":{"blue-default":"var(--r-blue-default, #7084ff)","blue-light1":"var(--r-blue-light1, #eef1ff)","blue-light-1":"var(--r-blue-light-1, #eef1ff)","blue-light2":"var(--r-blue-light2, #dee3fc)","blue-light-2":"var(--r-blue-light-2, #dee3fc)","blue-disable":"var(--r-blue-disable, #dbe0ff)","green-default":"var(--r-green-default, #2abb7f)","green-light":"var(--r-green-light, #d8f2e7)","orange-default":"var(--r-orange-default, #ffb020)","orange-light":"var(--r-orange-light, #fff5e2)","red-default":"var(--r-red-default, #e34935)","red-light":"var(--r-red-light, #fff2f0)","red-dark":"var(--r-red-dark, #ae2a19)","red-light2":"var(--r-red-light2, #efd4d1)","red-light-2":"var(--r-red-light-2, #efd4d1)","neutral-title1":"var(--r-neutral-title1, #192945)","neutral-title-1":"var(--r-neutral-title-1, #192945)","neutral-body":"var(--r-neutral-body, #3e495e)","neutral-foot":"var(--r-neutral-foot, #6a7587)","neutral-line":"var(--r-neutral-line, #d3d8e0)","neutral-bg1":"var(--r-neutral-bg1, #ffffff)","neutral-bg-1":"var(--r-neutral-bg-1, #ffffff)","neutral-bg2":"var(--r-neutral-bg2, #f2f4f7)","neutral-bg-2":"var(--r-neutral-bg-2, #f2f4f7)","neutral-bg3":"var(--r-neutral-bg3, #f7fafc)","neutral-bg-3":"var(--r-neutral-bg-3, #f7fafc)","neutral-card1":"var(--r-neutral-card1, #ffffff)","neutral-card-1":"var(--r-neutral-card-1, #ffffff)","neutral-card2":"var(--r-neutral-card2, #f2f4f7)","neutral-card-2":"var(--r-neutral-card-2, #f2f4f7)","neutral-card3":"var(--r-neutral-card3, #f7fafc)","neutral-card-3":"var(--r-neutral-card-3, #f7fafc)","neutral-title2":"var(--r-neutral-title2, #ffffff)","neutral-title-2":"var(--r-neutral-title-2, #ffffff)","neutral-black":"var(--r-neutral-black, #000000)"},"light-r":{"blue-default":"#7084ff","blue-light1":"#eef1ff","blue-light-1":"#eef1ff","blue-light2":"#dee3fc","blue-light-2":"#dee3fc","blue-disable":"#dbe0ff","green-default":"#2abb7f","green-light":"#d8f2e7","orange-default":"#ffb020","orange-light":"#fff5e2","red-default":"#e34935","red-light":"#fff2f0","red-dark":"#ae2a19","red-light2":"#efd4d1","red-light-2":"#efd4d1","neutral-title1":"#192945","neutral-title-1":"#192945","neutral-body":"#3e495e","neutral-foot":"#6a7587","neutral-line":"#d3d8e0","neutral-bg1":"#ffffff","neutral-bg-1":"#ffffff","neutral-bg2":"#f2f4f7","neutral-bg-2":"#f2f4f7","neutral-bg3":"#f7fafc","neutral-bg-3":"#f7fafc","neutral-card1":"#ffffff","neutral-card-1":"#ffffff","neutral-card2":"#f2f4f7","neutral-card-2":"#f2f4f7","neutral-card3":"#f7fafc","neutral-card-3":"#f7fafc","neutral-title2":"#ffffff","neutral-title-2":"#ffffff","neutral-black":"#000000"},"dark-r":{"blue-default":"#7084ff","blue-light1":"#424962","blue-light-1":"#424962","blue-light2":"#424962","blue-light-2":"#424962","blue-disable":"#4c5685","green-default":"#2abb7f","green-light":"#395a5a","orange-default":"#ffc64a","orange-light":"#484339","red-default":"#ef5c48","red-light":"#4f3a42","red-dark":"#ae2a19","red-light2":"#4f3a42","red-light-2":"#4f3a42","neutral-title1":"#f7fafc","neutral-title-1":"#f7fafc","neutral-body":"#d3d8e0","neutral-foot":"#babec5","neutral-line":"#ffffff1a","neutral-bg1":"#1c1f2b","neutral-bg-1":"#1c1f2b","neutral-bg2":"#1c1f2b","neutral-bg-2":"#1c1f2b","neutral-bg3":"#1c1f2b","neutral-bg-3":"#1c1f2b","neutral-card1":"#ffffff0f","neutral-card-1":"#ffffff0f","neutral-card2":"#ffffff0f","neutral-card-2":"#ffffff0f","neutral-card3":"#ffffff0f","neutral-card-3":"#ffffff0f","neutral-title2":"#ffffff","neutral-title-2":"#ffffff","neutral-black":"#000000"}},"fontSize":{"12":["12px",{"lineHeight":"14px"}],"13":"13px","14":["14px",{"lineHeight":"18px"}],"15":["15px",{"lineHeight":"18px"}],"18":["18px",{"lineHeight":"22px"}],"20":"20px","24":["24px",{"lineHeight":"28px"}],"28":["28px",{"lineHeight":"33px"}]},"animation":{"none":"none","spin":"spin 1s linear infinite","ping":"ping 1s cubic-bezier(0, 0, 0.2, 1) infinite","pulse":"pulse 2s cubic-bezier(0.4, 0, 0.6, 1) infinite","bounce":"bounce 1s infinite"},"backdropBlur":{"0":"0","none":"0","sm":"4px","DEFAULT":"8px","md":"12px","lg":"16px","xl":"24px","2xl":"40px","3xl":"64px"},"backdropBrightness":{"0":"0","50":".5","75":".75","90":".9","95":".95","100":"1","105":"1.05","110":"1.1","125":"1.25","150":"1.5","200":"2"},"backdropContrast":{"0":"0","50":".5","75":".75","100":"1","125":"1.25","150":"1.5","200":"2"},"backdropGrayscale":{"0":"0","DEFAULT":"100%"},"backdropHueRotate":{"0":"0deg","15":"15deg","30":"30deg","60":"60deg","90":"90deg","180":"180deg","-180":"-180deg","-90":"-90deg","-60":"-60deg","-30":"-30deg","-15":"-15deg"},"backdropInvert":{"0":"0","DEFAULT":"100%"},"backdropOpacity":{"0":"0","5":"0.05","10":"0.1","20":"0.2","25":"0.25","30":"0.3","40":"0.4","50":"0.5","60":"0.6","70":"0.7","75":"0.75","80":"0.8","90":"0.9","95":"0.95","100":"1"},"backdropSaturate":{"0":"0","50":".5","100":"1","150":"1.5","200":"2"},"backdropSepia":{"0":"0","DEFAULT":"100%"},"backgroundColor":{"transparent":"transparent","current":"currentColor","blue":{"from":"#8A78FD","to":"#796BFD","light":"#7084ff","DEFAULT":"#796BFD","purple":"#5F75FF"},"black":"#707280","green":"#27C193","white":"#fff","yellow":"#F29C1B","orange":"#FFB020","pink":"#F24822","red":{"light":"#F24822","DEFAULT":"#AF160E","forbidden":"#EC5151"},"gray":{"bg2":"#F5F6FA","bg":"#F5F6FA","divider":"#E5E9EF","comment":"#B4BDCC","content":"#707280","subTitle":"#4B4D59","title":"#13141A","light":"#707880","common":"#666666"},"r":{"blue-default":"var(--r-blue-default, #7084ff)","blue-light1":"var(--r-blue-light1, #eef1ff)","blue-light-1":"var(--r-blue-light-1, #eef1ff)","blue-light2":"var(--r-blue-light2, #dee3fc)","blue-light-2":"var(--r-blue-light-2, #dee3fc)","blue-disable":"var(--r-blue-disable, #dbe0ff)","green-default":"var(--r-green-default, #2abb7f)","green-light":"var(--r-green-light, #d8f2e7)","orange-default":"var(--r-orange-default, #ffb020)","orange-light":"var(--r-orange-light, #fff5e2)","red-default":"var(--r-red-default, #e34935)","red-light":"var(--r-red-light, #fff2f0)","red-dark":"var(--r-red-dark, #ae2a19)","red-light2":"var(--r-red-light2, #efd4d1)","red-light-2":"var(--r-red-light-2, #efd4d1)","neutral-title1":"var(--r-neutral-title1, #192945)","neutral-title-1":"var(--r-neutral-title-1, #192945)","neutral-body":"var(--r-neutral-body, #3e495e)","neutral-foot":"var(--r-neutral-foot, #6a7587)","neutral-line":"var(--r-neutral-line, #d3d8e0)","neutral-bg1":"var(--r-neutral-bg1, #ffffff)","neutral-bg-1":"var(--r-neutral-bg-1, #ffffff)","neutral-bg2":"var(--r-neutral-bg2, #f2f4f7)","neutral-bg-2":"var(--r-neutral-bg-2, #f2f4f7)","neutral-bg3":"var(--r-neutral-bg3, #f7fafc)","neutral-bg-3":"var(--r-neutral-bg-3, #f7fafc)","neutral-card1":"var(--r-neutral-card1, #ffffff)","neutral-card-1":"var(--r-neutral-card-1, #ffffff)","neutral-card2":"var(--r-neutral-card2, #f2f4f7)","neutral-card-2":"var(--r-neutral-card-2, #f2f4f7)","neutral-card3":"var(--r-neutral-card3, #f7fafc)","neutral-card-3":"var(--r-neutral-card-3, #f7fafc)","neutral-title2":"var(--r-neutral-title2, #ffffff)","neutral-title-2":"var(--r-neutral-title-2, #ffffff)","neutral-black":"var(--r-neutral-black, #000000)"},"rabby":{"blue-default":"var(--r-blue-default, #7084ff)","blue-light1":"var(--r-blue-light1, #eef1ff)","blue-light-1":"var(--r-blue-light-1, #eef1ff)","blue-light2":"var(--r-blue-light2, #dee3fc)","blue-light-2":"var(--r-blue-light-2, #dee3fc)","blue-disable":"var(--r-blue-disable, #dbe0ff)","green-default":"var(--r-green-default, #2abb7f)","green-light":"var(--r-green-light, #d8f2e7)","orange-default":"var(--r-orange-default, #ffb020)","orange-light":"var(--r-orange-light, #fff5e2)","red-default":"var(--r-red-default, #e34935)","red-light":"var(--r-red-light, #fff2f0)","red-dark":"var(--r-red-dark, #ae2a19)","red-light2":"var(--r-red-light2, #efd4d1)","red-light-2":"var(--r-red-light-2, #efd4d1)","neutral-title1":"var(--r-neutral-title1, #192945)","neutral-title-1":"var(--r-neutral-title-1, #192945)","neutral-body":"var(--r-neutral-body, #3e495e)","neutral-foot":"var(--r-neutral-foot, #6a7587)","neutral-line":"var(--r-neutral-line, #d3d8e0)","neutral-bg1":"var(--r-neutral-bg1, #ffffff)","neutral-bg-1":"var(--r-neutral-bg-1, #ffffff)","neutral-bg2":"var(--r-neutral-bg2, #f2f4f7)","neutral-bg-2":"var(--r-neutral-bg-2, #f2f4f7)","neutral-bg3":"var(--r-neutral-bg3, #f7fafc)","neutral-bg-3":"var(--r-neutral-bg-3, #f7fafc)","neutral-card1":"var(--r-neutral-card1, #ffffff)","neutral-card-1":"var(--r-neutral-card-1, #ffffff)","neutral-card2":"var(--r-neutral-card2, #f2f4f7)","neutral-card-2":"var(--r-neutral-card-2, #f2f4f7)","neutral-card3":"var(--r-neutral-card3, #f7fafc)","neutral-card-3":"var(--r-neutral-card-3, #f7fafc)","neutral-title2":"var(--r-neutral-title2, #ffffff)","neutral-title-2":"var(--r-neutral-title-2, #ffffff)","neutral-black":"var(--r-neutral-black, #000000)"},"-r":{"blue-default":"var(--r-blue-default, #7084ff)","blue-light1":"var(--r-blue-light1, #eef1ff)","blue-light-1":"var(--r-blue-light-1, #eef1ff)","blue-light2":"var(--r-blue-light2, #dee3fc)","blue-light-2":"var(--r-blue-light-2, #dee3fc)","blue-disable":"var(--r-blue-disable, #dbe0ff)","green-default":"var(--r-green-default, #2abb7f)","green-light":"var(--r-green-light, #d8f2e7)","orange-default":"var(--r-orange-default, #ffb020)","orange-light":"var(--r-orange-light, #fff5e2)","red-default":"var(--r-red-default, #e34935)","red-light":"var(--r-red-light, #fff2f0)","red-dark":"var(--r-red-dark, #ae2a19)","red-light2":"var(--r-red-light2, #efd4d1)","red-light-2":"var(--r-red-light-2, #efd4d1)","neutral-title1":"var(--r-neutral-title1, #192945)","neutral-title-1":"var(--r-neutral-title-1, #192945)","neutral-body":"var(--r-neutral-body, #3e495e)","neutral-foot":"var(--r-neutral-foot, #6a7587)","neutral-line":"var(--r-neutral-line, #d3d8e0)","neutral-bg1":"var(--r-neutral-bg1, #ffffff)","neutral-bg-1":"var(--r-neutral-bg-1, #ffffff)","neutral-bg2":"var(--r-neutral-bg2, #f2f4f7)","neutral-bg-2":"var(--r-neutral-bg-2, #f2f4f7)","neutral-bg3":"var(--r-neutral-bg3, #f7fafc)","neutral-bg-3":"var(--r-neutral-bg-3, #f7fafc)","neutral-card1":"var(--r-neutral-card1, #ffffff)","neutral-card-1":"var(--r-neutral-card-1, #ffffff)","neutral-card2":"var(--r-neutral-card2, #f2f4f7)","neutral-card-2":"var(--r-neutral-card-2, #f2f4f7)","neutral-card3":"var(--r-neutral-card3, #f7fafc)","neutral-card-3":"var(--r-neutral-card-3, #f7fafc)","neutral-title2":"var(--r-neutral-title2, #ffffff)","neutral-title-2":"var(--r-neutral-title-2, #ffffff)","neutral-black":"var(--r-neutral-black, #000000)"},"light-r":{"blue-default":"#7084ff","blue-light1":"#eef1ff","blue-light-1":"#eef1ff","blue-light2":"#dee3fc","blue-light-2":"#dee3fc","blue-disable":"#dbe0ff","green-default":"#2abb7f","green-light":"#d8f2e7","orange-default":"#ffb020","orange-light":"#fff5e2","red-default":"#e34935","red-light":"#fff2f0","red-dark":"#ae2a19","red-light2":"#efd4d1","red-light-2":"#efd4d1","neutral-title1":"#192945","neutral-title-1":"#192945","neutral-body":"#3e495e","neutral-foot":"#6a7587","neutral-line":"#d3d8e0","neutral-bg1":"#ffffff","neutral-bg-1":"#ffffff","neutral-bg2":"#f2f4f7","neutral-bg-2":"#f2f4f7","neutral-bg3":"#f7fafc","neutral-bg-3":"#f7fafc","neutral-card1":"#ffffff","neutral-card-1":"#ffffff","neutral-card2":"#f2f4f7","neutral-card-2":"#f2f4f7","neutral-card3":"#f7fafc","neutral-card-3":"#f7fafc","neutral-title2":"#ffffff","neutral-title-2":"#ffffff","neutral-black":"#000000"},"dark-r":{"blue-default":"#7084ff","blue-light1":"#424962","blue-light-1":"#424962","blue-light2":"#424962","blue-light-2":"#424962","blue-disable":"#4c5685","green-default":"#2abb7f","green-light":"#395a5a","orange-default":"#ffc64a","orange-light":"#484339","red-default":"#ef5c48","red-light":"#4f3a42","red-dark":"#ae2a19","red-light2":"#4f3a42","red-light-2":"#4f3a42","neutral-title1":"#f7fafc","neutral-title-1":"#f7fafc","neutral-body":"#d3d8e0","neutral-foot":"#babec5","neutral-line":"#ffffff1a","neutral-bg1":"#1c1f2b","neutral-bg-1":"#1c1f2b","neutral-bg2":"#1c1f2b","neutral-bg-2":"#1c1f2b","neutral-bg3":"#1c1f2b","neutral-bg-3":"#1c1f2b","neutral-card1":"#ffffff0f","neutral-card-1":"#ffffff0f","neutral-card2":"#ffffff0f","neutral-card-2":"#ffffff0f","neutral-card3":"#ffffff0f","neutral-card-3":"#ffffff0f","neutral-title2":"#ffffff","neutral-title-2":"#ffffff","neutral-black":"#000000"}},"backgroundImage":{"none":"none","gradient-to-t":"linear-gradient(to top, var(--tw-gradient-stops))","gradient-to-tr":"linear-gradient(to top right, var(--tw-gradient-stops))","gradient-to-r":"linear-gradient(to right, var(--tw-gradient-stops))","gradient-to-br":"linear-gradient(to bottom right, var(--tw-gradient-stops))","gradient-to-b":"linear-gradient(to bottom, var(--tw-gradient-stops))","gradient-to-bl":"linear-gradient(to bottom left, var(--tw-gradient-stops))","gradient-to-l":"linear-gradient(to left, var(--tw-gradient-stops))","gradient-to-tl":"linear-gradient(to top left, var(--tw-gradient-stops))"},"backgroundOpacity":{"0":"0","5":"0.05","10":"0.1","20":"0.2","25":"0.25","30":"0.3","40":"0.4","50":"0.5","60":"0.6","70":"0.7","75":"0.75","80":"0.8","90":"0.9","95":"0.95","100":"1"},"backgroundPosition":{"bottom":"bottom","center":"center","left":"left","left-bottom":"left bottom","left-top":"left top","right":"right","right-bottom":"right bottom","right-top":"right top","top":"top"},"backgroundSize":{"auto":"auto","cover":"cover","contain":"contain"},"blur":{"0":"0","none":"0","sm":"4px","DEFAULT":"8px","md":"12px","lg":"16px","xl":"24px","2xl":"40px","3xl":"64px"},"brightness":{"0":"0","50":".5","75":".75","90":".9","95":".95","100":"1","105":"1.05","110":"1.1","125":"1.25","150":"1.5","200":"2"},"borderColor":{"transparent":"transparent","current":"currentColor","blue":{"from":"#8A78FD","to":"#796BFD","light":"#7084ff","DEFAULT":"#796BFD","purple":"#5F75FF"},"black":"#707280","green":"#27C193","white":"#fff","yellow":"#F29C1B","orange":"#FFB020","pink":"#F24822","red":{"light":"#F24822","DEFAULT":"#AF160E","forbidden":"#EC5151"},"gray":{"bg2":"#F5F6FA","bg":"#F5F6FA","divider":"#E5E9EF","comment":"#B4BDCC","content":"#707280","subTitle":"#4B4D59","title":"#13141A","light":"#707880","common":"#666666"},"r":{"blue-default":"var(--r-blue-default, #7084ff)","blue-light1":"var(--r-blue-light1, #eef1ff)","blue-light-1":"var(--r-blue-light-1, #eef1ff)","blue-light2":"var(--r-blue-light2, #dee3fc)","blue-light-2":"var(--r-blue-light-2, #dee3fc)","blue-disable":"var(--r-blue-disable, #dbe0ff)","green-default":"var(--r-green-default, #2abb7f)","green-light":"var(--r-green-light, #d8f2e7)","orange-default":"var(--r-orange-default, #ffb020)","orange-light":"var(--r-orange-light, #fff5e2)","red-default":"var(--r-red-default, #e34935)","red-light":"var(--r-red-light, #fff2f0)","red-dark":"var(--r-red-dark, #ae2a19)","red-light2":"var(--r-red-light2, #efd4d1)","red-light-2":"var(--r-red-light-2, #efd4d1)","neutral-title1":"var(--r-neutral-title1, #192945)","neutral-title-1":"var(--r-neutral-title-1, #192945)","neutral-body":"var(--r-neutral-body, #3e495e)","neutral-foot":"var(--r-neutral-foot, #6a7587)","neutral-line":"var(--r-neutral-line, #d3d8e0)","neutral-bg1":"var(--r-neutral-bg1, #ffffff)","neutral-bg-1":"var(--r-neutral-bg-1, #ffffff)","neutral-bg2":"var(--r-neutral-bg2, #f2f4f7)","neutral-bg-2":"var(--r-neutral-bg-2, #f2f4f7)","neutral-bg3":"var(--r-neutral-bg3, #f7fafc)","neutral-bg-3":"var(--r-neutral-bg-3, #f7fafc)","neutral-card1":"var(--r-neutral-card1, #ffffff)","neutral-card-1":"var(--r-neutral-card-1, #ffffff)","neutral-card2":"var(--r-neutral-card2, #f2f4f7)","neutral-card-2":"var(--r-neutral-card-2, #f2f4f7)","neutral-card3":"var(--r-neutral-card3, #f7fafc)","neutral-card-3":"var(--r-neutral-card-3, #f7fafc)","neutral-title2":"var(--r-neutral-title2, #ffffff)","neutral-title-2":"var(--r-neutral-title-2, #ffffff)","neutral-black":"var(--r-neutral-black, #000000)"},"rabby":{"blue-default":"var(--r-blue-default, #7084ff)","blue-light1":"var(--r-blue-light1, #eef1ff)","blue-light-1":"var(--r-blue-light-1, #eef1ff)","blue-light2":"var(--r-blue-light2, #dee3fc)","blue-light-2":"var(--r-blue-light-2, #dee3fc)","blue-disable":"var(--r-blue-disable, #dbe0ff)","green-default":"var(--r-green-default, #2abb7f)","green-light":"var(--r-green-light, #d8f2e7)","orange-default":"var(--r-orange-default, #ffb020)","orange-light":"var(--r-orange-light, #fff5e2)","red-default":"var(--r-red-default, #e34935)","red-light":"var(--r-red-light, #fff2f0)","red-dark":"var(--r-red-dark, #ae2a19)","red-light2":"var(--r-red-light2, #efd4d1)","red-light-2":"var(--r-red-light-2, #efd4d1)","neutral-title1":"var(--r-neutral-title1, #192945)","neutral-title-1":"var(--r-neutral-title-1, #192945)","neutral-body":"var(--r-neutral-body, #3e495e)","neutral-foot":"var(--r-neutral-foot, #6a7587)","neutral-line":"var(--r-neutral-line, #d3d8e0)","neutral-bg1":"var(--r-neutral-bg1, #ffffff)","neutral-bg-1":"var(--r-neutral-bg-1, #ffffff)","neutral-bg2":"var(--r-neutral-bg2, #f2f4f7)","neutral-bg-2":"var(--r-neutral-bg-2, #f2f4f7)","neutral-bg3":"var(--r-neutral-bg3, #f7fafc)","neutral-bg-3":"var(--r-neutral-bg-3, #f7fafc)","neutral-card1":"var(--r-neutral-card1, #ffffff)","neutral-card-1":"var(--r-neutral-card-1, #ffffff)","neutral-card2":"var(--r-neutral-card2, #f2f4f7)","neutral-card-2":"var(--r-neutral-card-2, #f2f4f7)","neutral-card3":"var(--r-neutral-card3, #f7fafc)","neutral-card-3":"var(--r-neutral-card-3, #f7fafc)","neutral-title2":"var(--r-neutral-title2, #ffffff)","neutral-title-2":"var(--r-neutral-title-2, #ffffff)","neutral-black":"var(--r-neutral-black, #000000)"},"-r":{"blue-default":"var(--r-blue-default, #7084ff)","blue-light1":"var(--r-blue-light1, #eef1ff)","blue-light-1":"var(--r-blue-light-1, #eef1ff)","blue-light2":"var(--r-blue-light2, #dee3fc)","blue-light-2":"var(--r-blue-light-2, #dee3fc)","blue-disable":"var(--r-blue-disable, #dbe0ff)","green-default":"var(--r-green-default, #2abb7f)","green-light":"var(--r-green-light, #d8f2e7)","orange-default":"var(--r-orange-default, #ffb020)","orange-light":"var(--r-orange-light, #fff5e2)","red-default":"var(--r-red-default, #e34935)","red-light":"var(--r-red-light, #fff2f0)","red-dark":"var(--r-red-dark, #ae2a19)","red-light2":"var(--r-red-light2, #efd4d1)","red-light-2":"var(--r-red-light-2, #efd4d1)","neutral-title1":"var(--r-neutral-title1, #192945)","neutral-title-1":"var(--r-neutral-title-1, #192945)","neutral-body":"var(--r-neutral-body, #3e495e)","neutral-foot":"var(--r-neutral-foot, #6a7587)","neutral-line":"var(--r-neutral-line, #d3d8e0)","neutral-bg1":"var(--r-neutral-bg1, #ffffff)","neutral-bg-1":"var(--r-neutral-bg-1, #ffffff)","neutral-bg2":"var(--r-neutral-bg2, #f2f4f7)","neutral-bg-2":"var(--r-neutral-bg-2, #f2f4f7)","neutral-bg3":"var(--r-neutral-bg3, #f7fafc)","neutral-bg-3":"var(--r-neutral-bg-3, #f7fafc)","neutral-card1":"var(--r-neutral-card1, #ffffff)","neutral-card-1":"var(--r-neutral-card-1, #ffffff)","neutral-card2":"var(--r-neutral-card2, #f2f4f7)","neutral-card-2":"var(--r-neutral-card-2, #f2f4f7)","neutral-card3":"var(--r-neutral-card3, #f7fafc)","neutral-card-3":"var(--r-neutral-card-3, #f7fafc)","neutral-title2":"var(--r-neutral-title2, #ffffff)","neutral-title-2":"var(--r-neutral-title-2, #ffffff)","neutral-black":"var(--r-neutral-black, #000000)"},"light-r":{"blue-default":"#7084ff","blue-light1":"#eef1ff","blue-light-1":"#eef1ff","blue-light2":"#dee3fc","blue-light-2":"#dee3fc","blue-disable":"#dbe0ff","green-default":"#2abb7f","green-light":"#d8f2e7","orange-default":"#ffb020","orange-light":"#fff5e2","red-default":"#e34935","red-light":"#fff2f0","red-dark":"#ae2a19","red-light2":"#efd4d1","red-light-2":"#efd4d1","neutral-title1":"#192945","neutral-title-1":"#192945","neutral-body":"#3e495e","neutral-foot":"#6a7587","neutral-line":"#d3d8e0","neutral-bg1":"#ffffff","neutral-bg-1":"#ffffff","neutral-bg2":"#f2f4f7","neutral-bg-2":"#f2f4f7","neutral-bg3":"#f7fafc","neutral-bg-3":"#f7fafc","neutral-card1":"#ffffff","neutral-card-1":"#ffffff","neutral-card2":"#f2f4f7","neutral-card-2":"#f2f4f7","neutral-card3":"#f7fafc","neutral-card-3":"#f7fafc","neutral-title2":"#ffffff","neutral-title-2":"#ffffff","neutral-black":"#000000"},"dark-r":{"blue-default":"#7084ff","blue-light1":"#424962","blue-light-1":"#424962","blue-light2":"#424962","blue-light-2":"#424962","blue-disable":"#4c5685","green-default":"#2abb7f","green-light":"#395a5a","orange-default":"#ffc64a","orange-light":"#484339","red-default":"#ef5c48","red-light":"#4f3a42","red-dark":"#ae2a19","red-light2":"#4f3a42","red-light-2":"#4f3a42","neutral-title1":"#f7fafc","neutral-title-1":"#f7fafc","neutral-body":"#d3d8e0","neutral-foot":"#babec5","neutral-line":"#ffffff1a","neutral-bg1":"#1c1f2b","neutral-bg-1":"#1c1f2b","neutral-bg2":"#1c1f2b","neutral-bg-2":"#1c1f2b","neutral-bg3":"#1c1f2b","neutral-bg-3":"#1c1f2b","neutral-card1":"#ffffff0f","neutral-card-1":"#ffffff0f","neutral-card2":"#ffffff0f","neutral-card-2":"#ffffff0f","neutral-card3":"#ffffff0f","neutral-card-3":"#ffffff0f","neutral-title2":"#ffffff","neutral-title-2":"#ffffff","neutral-black":"#000000"},"DEFAULT":"currentColor"},"borderOpacity":{"0":"0","5":"0.05","10":"0.1","20":"0.2","25":"0.25","30":"0.3","40":"0.4","50":"0.5","60":"0.6","70":"0.7","75":"0.75","80":"0.8","90":"0.9","95":"0.95","100":"1"},"borderRadius":{"none":"0px","sm":"0.125rem","DEFAULT":"0.25rem","md":"0.375rem","lg":"0.5rem","xl":"0.75rem","2xl":"1rem","3xl":"1.5rem","full":"9999px"},"borderWidth":{"0":"0px","2":"2px","4":"4px","8":"8px","DEFAULT":"1px"},"boxShadow":{"sm":"0 1px 2px 0 rgba(0, 0, 0, 0.05)","DEFAULT":"0 1px 3px 0 rgba(0, 0, 0, 0.1), 0 1px 2px 0 rgba(0, 0, 0, 0.06)","md":"0 4px 6px -1px rgba(0, 0, 0, 0.1), 0 2px 4px -1px rgba(0, 0, 0, 0.06)","lg":"0 10px 15px -3px rgba(0, 0, 0, 0.1), 0 4px 6px -2px rgba(0, 0, 0, 0.05)","xl":"0 20px 25px -5px rgba(0, 0, 0, 0.1), 0 10px 10px -5px rgba(0, 0, 0, 0.04)","2xl":"0 25px 50px -12px rgba(0, 0, 0, 0.25)","inner":"inset 0 2px 4px 0 rgba(0, 0, 0, 0.06)","none":"none"},"caretColor":{"transparent":"transparent","current":"currentColor","blue":{"from":"#8A78FD","to":"#796BFD","light":"#7084ff","DEFAULT":"#796BFD","purple":"#5F75FF"},"black":"#707280","green":"#27C193","white":"#fff","yellow":"#F29C1B","orange":"#FFB020","pink":"#F24822","red":{"light":"#F24822","DEFAULT":"#AF160E","forbidden":"#EC5151"},"gray":{"bg2":"#F5F6FA","bg":"#F5F6FA","divider":"#E5E9EF","comment":"#B4BDCC","content":"#707280","subTitle":"#4B4D59","title":"#13141A","light":"#707880","common":"#666666"},"r":{"blue-default":"var(--r-blue-default, #7084ff)","blue-light1":"var(--r-blue-light1, #eef1ff)","blue-light-1":"var(--r-blue-light-1, #eef1ff)","blue-light2":"var(--r-blue-light2, #dee3fc)","blue-light-2":"var(--r-blue-light-2, #dee3fc)","blue-disable":"var(--r-blue-disable, #dbe0ff)","green-default":"var(--r-green-default, #2abb7f)","green-light":"var(--r-green-light, #d8f2e7)","orange-default":"var(--r-orange-default, #ffb020)","orange-light":"var(--r-orange-light, #fff5e2)","red-default":"var(--r-red-default, #e34935)","red-light":"var(--r-red-light, #fff2f0)","red-dark":"var(--r-red-dark, #ae2a19)","red-light2":"var(--r-red-light2, #efd4d1)","red-light-2":"var(--r-red-light-2, #efd4d1)","neutral-title1":"var(--r-neutral-title1, #192945)","neutral-title-1":"var(--r-neutral-title-1, #192945)","neutral-body":"var(--r-neutral-body, #3e495e)","neutral-foot":"var(--r-neutral-foot, #6a7587)","neutral-line":"var(--r-neutral-line, #d3d8e0)","neutral-bg1":"var(--r-neutral-bg1, #ffffff)","neutral-bg-1":"var(--r-neutral-bg-1, #ffffff)","neutral-bg2":"var(--r-neutral-bg2, #f2f4f7)","neutral-bg-2":"var(--r-neutral-bg-2, #f2f4f7)","neutral-bg3":"var(--r-neutral-bg3, #f7fafc)","neutral-bg-3":"var(--r-neutral-bg-3, #f7fafc)","neutral-card1":"var(--r-neutral-card1, #ffffff)","neutral-card-1":"var(--r-neutral-card-1, #ffffff)","neutral-card2":"var(--r-neutral-card2, #f2f4f7)","neutral-card-2":"var(--r-neutral-card-2, #f2f4f7)","neutral-card3":"var(--r-neutral-card3, #f7fafc)","neutral-card-3":"var(--r-neutral-card-3, #f7fafc)","neutral-title2":"var(--r-neutral-title2, #ffffff)","neutral-title-2":"var(--r-neutral-title-2, #ffffff)","neutral-black":"var(--r-neutral-black, #000000)"},"rabby":{"blue-default":"var(--r-blue-default, #7084ff)","blue-light1":"var(--r-blue-light1, #eef1ff)","blue-light-1":"var(--r-blue-light-1, #eef1ff)","blue-light2":"var(--r-blue-light2, #dee3fc)","blue-light-2":"var(--r-blue-light-2, #dee3fc)","blue-disable":"var(--r-blue-disable, #dbe0ff)","green-default":"var(--r-green-default, #2abb7f)","green-light":"var(--r-green-light, #d8f2e7)","orange-default":"var(--r-orange-default, #ffb020)","orange-light":"var(--r-orange-light, #fff5e2)","red-default":"var(--r-red-default, #e34935)","red-light":"var(--r-red-light, #fff2f0)","red-dark":"var(--r-red-dark, #ae2a19)","red-light2":"var(--r-red-light2, #efd4d1)","red-light-2":"var(--r-red-light-2, #efd4d1)","neutral-title1":"var(--r-neutral-title1, #192945)","neutral-title-1":"var(--r-neutral-title-1, #192945)","neutral-body":"var(--r-neutral-body, #3e495e)","neutral-foot":"var(--r-neutral-foot, #6a7587)","neutral-line":"var(--r-neutral-line, #d3d8e0)","neutral-bg1":"var(--r-neutral-bg1, #ffffff)","neutral-bg-1":"var(--r-neutral-bg-1, #ffffff)","neutral-bg2":"var(--r-neutral-bg2, #f2f4f7)","neutral-bg-2":"var(--r-neutral-bg-2, #f2f4f7)","neutral-bg3":"var(--r-neutral-bg3, #f7fafc)","neutral-bg-3":"var(--r-neutral-bg-3, #f7fafc)","neutral-card1":"var(--r-neutral-card1, #ffffff)","neutral-card-1":"var(--r-neutral-card-1, #ffffff)","neutral-card2":"var(--r-neutral-card2, #f2f4f7)","neutral-card-2":"var(--r-neutral-card-2, #f2f4f7)","neutral-card3":"var(--r-neutral-card3, #f7fafc)","neutral-card-3":"var(--r-neutral-card-3, #f7fafc)","neutral-title2":"var(--r-neutral-title2, #ffffff)","neutral-title-2":"var(--r-neutral-title-2, #ffffff)","neutral-black":"var(--r-neutral-black, #000000)"},"-r":{"blue-default":"var(--r-blue-default, #7084ff)","blue-light1":"var(--r-blue-light1, #eef1ff)","blue-light-1":"var(--r-blue-light-1, #eef1ff)","blue-light2":"var(--r-blue-light2, #dee3fc)","blue-light-2":"var(--r-blue-light-2, #dee3fc)","blue-disable":"var(--r-blue-disable, #dbe0ff)","green-default":"var(--r-green-default, #2abb7f)","green-light":"var(--r-green-light, #d8f2e7)","orange-default":"var(--r-orange-default, #ffb020)","orange-light":"var(--r-orange-light, #fff5e2)","red-default":"var(--r-red-default, #e34935)","red-light":"var(--r-red-light, #fff2f0)","red-dark":"var(--r-red-dark, #ae2a19)","red-light2":"var(--r-red-light2, #efd4d1)","red-light-2":"var(--r-red-light-2, #efd4d1)","neutral-title1":"var(--r-neutral-title1, #192945)","neutral-title-1":"var(--r-neutral-title-1, #192945)","neutral-body":"var(--r-neutral-body, #3e495e)","neutral-foot":"var(--r-neutral-foot, #6a7587)","neutral-line":"var(--r-neutral-line, #d3d8e0)","neutral-bg1":"var(--r-neutral-bg1, #ffffff)","neutral-bg-1":"var(--r-neutral-bg-1, #ffffff)","neutral-bg2":"var(--r-neutral-bg2, #f2f4f7)","neutral-bg-2":"var(--r-neutral-bg-2, #f2f4f7)","neutral-bg3":"var(--r-neutral-bg3, #f7fafc)","neutral-bg-3":"var(--r-neutral-bg-3, #f7fafc)","neutral-card1":"var(--r-neutral-card1, #ffffff)","neutral-card-1":"var(--r-neutral-card-1, #ffffff)","neutral-card2":"var(--r-neutral-card2, #f2f4f7)","neutral-card-2":"var(--r-neutral-card-2, #f2f4f7)","neutral-card3":"var(--r-neutral-card3, #f7fafc)","neutral-card-3":"var(--r-neutral-card-3, #f7fafc)","neutral-title2":"var(--r-neutral-title2, #ffffff)","neutral-title-2":"var(--r-neutral-title-2, #ffffff)","neutral-black":"var(--r-neutral-black, #000000)"},"light-r":{"blue-default":"#7084ff","blue-light1":"#eef1ff","blue-light-1":"#eef1ff","blue-light2":"#dee3fc","blue-light-2":"#dee3fc","blue-disable":"#dbe0ff","green-default":"#2abb7f","green-light":"#d8f2e7","orange-default":"#ffb020","orange-light":"#fff5e2","red-default":"#e34935","red-light":"#fff2f0","red-dark":"#ae2a19","red-light2":"#efd4d1","red-light-2":"#efd4d1","neutral-title1":"#192945","neutral-title-1":"#192945","neutral-body":"#3e495e","neutral-foot":"#6a7587","neutral-line":"#d3d8e0","neutral-bg1":"#ffffff","neutral-bg-1":"#ffffff","neutral-bg2":"#f2f4f7","neutral-bg-2":"#f2f4f7","neutral-bg3":"#f7fafc","neutral-bg-3":"#f7fafc","neutral-card1":"#ffffff","neutral-card-1":"#ffffff","neutral-card2":"#f2f4f7","neutral-card-2":"#f2f4f7","neutral-card3":"#f7fafc","neutral-card-3":"#f7fafc","neutral-title2":"#ffffff","neutral-title-2":"#ffffff","neutral-black":"#000000"},"dark-r":{"blue-default":"#7084ff","blue-light1":"#424962","blue-light-1":"#424962","blue-light2":"#424962","blue-light-2":"#424962","blue-disable":"#4c5685","green-default":"#2abb7f","green-light":"#395a5a","orange-default":"#ffc64a","orange-light":"#484339","red-default":"#ef5c48","red-light":"#4f3a42","red-dark":"#ae2a19","red-light2":"#4f3a42","red-light-2":"#4f3a42","neutral-title1":"#f7fafc","neutral-title-1":"#f7fafc","neutral-body":"#d3d8e0","neutral-foot":"#babec5","neutral-line":"#ffffff1a","neutral-bg1":"#1c1f2b","neutral-bg-1":"#1c1f2b","neutral-bg2":"#1c1f2b","neutral-bg-2":"#1c1f2b","neutral-bg3":"#1c1f2b","neutral-bg-3":"#1c1f2b","neutral-card1":"#ffffff0f","neutral-card-1":"#ffffff0f","neutral-card2":"#ffffff0f","neutral-card-2":"#ffffff0f","neutral-card3":"#ffffff0f","neutral-card-3":"#ffffff0f","neutral-title2":"#ffffff","neutral-title-2":"#ffffff","neutral-black":"#000000"}},"contrast":{"0":"0","50":".5","75":".75","100":"1","125":"1.25","150":"1.5","200":"2"},"container":{},"content":{"none":"none"},"cursor":{"auto":"auto","default":"default","pointer":"pointer","wait":"wait","text":"text","move":"move","help":"help","not-allowed":"not-allowed"},"divideColor":{"transparent":"transparent","current":"currentColor","blue":{"from":"#8A78FD","to":"#796BFD","light":"#7084ff","DEFAULT":"#796BFD","purple":"#5F75FF"},"black":"#707280","green":"#27C193","white":"#fff","yellow":"#F29C1B","orange":"#FFB020","pink":"#F24822","red":{"light":"#F24822","DEFAULT":"#AF160E","forbidden":"#EC5151"},"gray":{"bg2":"#F5F6FA","bg":"#F5F6FA","divider":"#E5E9EF","comment":"#B4BDCC","content":"#707280","subTitle":"#4B4D59","title":"#13141A","light":"#707880","common":"#666666"},"r":{"blue-default":"var(--r-blue-default, #7084ff)","blue-light1":"var(--r-blue-light1, #eef1ff)","blue-light-1":"var(--r-blue-light-1, #eef1ff)","blue-light2":"var(--r-blue-light2, #dee3fc)","blue-light-2":"var(--r-blue-light-2, #dee3fc)","blue-disable":"var(--r-blue-disable, #dbe0ff)","green-default":"var(--r-green-default, #2abb7f)","green-light":"var(--r-green-light, #d8f2e7)","orange-default":"var(--r-orange-default, #ffb020)","orange-light":"var(--r-orange-light, #fff5e2)","red-default":"var(--r-red-default, #e34935)","red-light":"var(--r-red-light, #fff2f0)","red-dark":"var(--r-red-dark, #ae2a19)","red-light2":"var(--r-red-light2, #efd4d1)","red-light-2":"var(--r-red-light-2, #efd4d1)","neutral-title1":"var(--r-neutral-title1, #192945)","neutral-title-1":"var(--r-neutral-title-1, #192945)","neutral-body":"var(--r-neutral-body, #3e495e)","neutral-foot":"var(--r-neutral-foot, #6a7587)","neutral-line":"var(--r-neutral-line, #d3d8e0)","neutral-bg1":"var(--r-neutral-bg1, #ffffff)","neutral-bg-1":"var(--r-neutral-bg-1, #ffffff)","neutral-bg2":"var(--r-neutral-bg2, #f2f4f7)","neutral-bg-2":"var(--r-neutral-bg-2, #f2f4f7)","neutral-bg3":"var(--r-neutral-bg3, #f7fafc)","neutral-bg-3":"var(--r-neutral-bg-3, #f7fafc)","neutral-card1":"var(--r-neutral-card1, #ffffff)","neutral-card-1":"var(--r-neutral-card-1, #ffffff)","neutral-card2":"var(--r-neutral-card2, #f2f4f7)","neutral-card-2":"var(--r-neutral-card-2, #f2f4f7)","neutral-card3":"var(--r-neutral-card3, #f7fafc)","neutral-card-3":"var(--r-neutral-card-3, #f7fafc)","neutral-title2":"var(--r-neutral-title2, #ffffff)","neutral-title-2":"var(--r-neutral-title-2, #ffffff)","neutral-black":"var(--r-neutral-black, #000000)"},"rabby":{"blue-default":"var(--r-blue-default, #7084ff)","blue-light1":"var(--r-blue-light1, #eef1ff)","blue-light-1":"var(--r-blue-light-1, #eef1ff)","blue-light2":"var(--r-blue-light2, #dee3fc)","blue-light-2":"var(--r-blue-light-2, #dee3fc)","blue-disable":"var(--r-blue-disable, #dbe0ff)","green-default":"var(--r-green-default, #2abb7f)","green-light":"var(--r-green-light, #d8f2e7)","orange-default":"var(--r-orange-default, #ffb020)","orange-light":"var(--r-orange-light, #fff5e2)","red-default":"var(--r-red-default, #e34935)","red-light":"var(--r-red-light, #fff2f0)","red-dark":"var(--r-red-dark, #ae2a19)","red-light2":"var(--r-red-light2, #efd4d1)","red-light-2":"var(--r-red-light-2, #efd4d1)","neutral-title1":"var(--r-neutral-title1, #192945)","neutral-title-1":"var(--r-neutral-title-1, #192945)","neutral-body":"var(--r-neutral-body, #3e495e)","neutral-foot":"var(--r-neutral-foot, #6a7587)","neutral-line":"var(--r-neutral-line, #d3d8e0)","neutral-bg1":"var(--r-neutral-bg1, #ffffff)","neutral-bg-1":"var(--r-neutral-bg-1, #ffffff)","neutral-bg2":"var(--r-neutral-bg2, #f2f4f7)","neutral-bg-2":"var(--r-neutral-bg-2, #f2f4f7)","neutral-bg3":"var(--r-neutral-bg3, #f7fafc)","neutral-bg-3":"var(--r-neutral-bg-3, #f7fafc)","neutral-card1":"var(--r-neutral-card1, #ffffff)","neutral-card-1":"var(--r-neutral-card-1, #ffffff)","neutral-card2":"var(--r-neutral-card2, #f2f4f7)","neutral-card-2":"var(--r-neutral-card-2, #f2f4f7)","neutral-card3":"var(--r-neutral-card3, #f7fafc)","neutral-card-3":"var(--r-neutral-card-3, #f7fafc)","neutral-title2":"var(--r-neutral-title2, #ffffff)","neutral-title-2":"var(--r-neutral-title-2, #ffffff)","neutral-black":"var(--r-neutral-black, #000000)"},"-r":{"blue-default":"var(--r-blue-default, #7084ff)","blue-light1":"var(--r-blue-light1, #eef1ff)","blue-light-1":"var(--r-blue-light-1, #eef1ff)","blue-light2":"var(--r-blue-light2, #dee3fc)","blue-light-2":"var(--r-blue-light-2, #dee3fc)","blue-disable":"var(--r-blue-disable, #dbe0ff)","green-default":"var(--r-green-default, #2abb7f)","green-light":"var(--r-green-light, #d8f2e7)","orange-default":"var(--r-orange-default, #ffb020)","orange-light":"var(--r-orange-light, #fff5e2)","red-default":"var(--r-red-default, #e34935)","red-light":"var(--r-red-light, #fff2f0)","red-dark":"var(--r-red-dark, #ae2a19)","red-light2":"var(--r-red-light2, #efd4d1)","red-light-2":"var(--r-red-light-2, #efd4d1)","neutral-title1":"var(--r-neutral-title1, #192945)","neutral-title-1":"var(--r-neutral-title-1, #192945)","neutral-body":"var(--r-neutral-body, #3e495e)","neutral-foot":"var(--r-neutral-foot, #6a7587)","neutral-line":"var(--r-neutral-line, #d3d8e0)","neutral-bg1":"var(--r-neutral-bg1, #ffffff)","neutral-bg-1":"var(--r-neutral-bg-1, #ffffff)","neutral-bg2":"var(--r-neutral-bg2, #f2f4f7)","neutral-bg-2":"var(--r-neutral-bg-2, #f2f4f7)","neutral-bg3":"var(--r-neutral-bg3, #f7fafc)","neutral-bg-3":"var(--r-neutral-bg-3, #f7fafc)","neutral-card1":"var(--r-neutral-card1, #ffffff)","neutral-card-1":"var(--r-neutral-card-1, #ffffff)","neutral-card2":"var(--r-neutral-card2, #f2f4f7)","neutral-card-2":"var(--r-neutral-card-2, #f2f4f7)","neutral-card3":"var(--r-neutral-card3, #f7fafc)","neutral-card-3":"var(--r-neutral-card-3, #f7fafc)","neutral-title2":"var(--r-neutral-title2, #ffffff)","neutral-title-2":"var(--r-neutral-title-2, #ffffff)","neutral-black":"var(--r-neutral-black, #000000)"},"light-r":{"blue-default":"#7084ff","blue-light1":"#eef1ff","blue-light-1":"#eef1ff","blue-light2":"#dee3fc","blue-light-2":"#dee3fc","blue-disable":"#dbe0ff","green-default":"#2abb7f","green-light":"#d8f2e7","orange-default":"#ffb020","orange-light":"#fff5e2","red-default":"#e34935","red-light":"#fff2f0","red-dark":"#ae2a19","red-light2":"#efd4d1","red-light-2":"#efd4d1","neutral-title1":"#192945","neutral-title-1":"#192945","neutral-body":"#3e495e","neutral-foot":"#6a7587","neutral-line":"#d3d8e0","neutral-bg1":"#ffffff","neutral-bg-1":"#ffffff","neutral-bg2":"#f2f4f7","neutral-bg-2":"#f2f4f7","neutral-bg3":"#f7fafc","neutral-bg-3":"#f7fafc","neutral-card1":"#ffffff","neutral-card-1":"#ffffff","neutral-card2":"#f2f4f7","neutral-card-2":"#f2f4f7","neutral-card3":"#f7fafc","neutral-card-3":"#f7fafc","neutral-title2":"#ffffff","neutral-title-2":"#ffffff","neutral-black":"#000000"},"dark-r":{"blue-default":"#7084ff","blue-light1":"#424962","blue-light-1":"#424962","blue-light2":"#424962","blue-light-2":"#424962","blue-disable":"#4c5685","green-default":"#2abb7f","green-light":"#395a5a","orange-default":"#ffc64a","orange-light":"#484339","red-default":"#ef5c48","red-light":"#4f3a42","red-dark":"#ae2a19","red-light2":"#4f3a42","red-light-2":"#4f3a42","neutral-title1":"#f7fafc","neutral-title-1":"#f7fafc","neutral-body":"#d3d8e0","neutral-foot":"#babec5","neutral-line":"#ffffff1a","neutral-bg1":"#1c1f2b","neutral-bg-1":"#1c1f2b","neutral-bg2":"#1c1f2b","neutral-bg-2":"#1c1f2b","neutral-bg3":"#1c1f2b","neutral-bg-3":"#1c1f2b","neutral-card1":"#ffffff0f","neutral-card-1":"#ffffff0f","neutral-card2":"#ffffff0f","neutral-card-2":"#ffffff0f","neutral-card3":"#ffffff0f","neutral-card-3":"#ffffff0f","neutral-title2":"#ffffff","neutral-title-2":"#ffffff","neutral-black":"#000000"},"DEFAULT":"currentColor"},"divideOpacity":{"0":"0","5":"0.05","10":"0.1","20":"0.2","25":"0.25","30":"0.3","40":"0.4","50":"0.5","60":"0.6","70":"0.7","75":"0.75","80":"0.8","90":"0.9","95":"0.95","100":"1"},"divideWidth":{"0":"0px","2":"2px","4":"4px","8":"8px","DEFAULT":"1px"},"dropShadow":{"sm":"0 1px 1px rgba(0,0,0,0.05)","DEFAULT":["0 1px 2px rgba(0, 0, 0, 0.1)","0 1px 1px rgba(0, 0, 0, 0.06)"],"md":["0 4px 3px rgba(0, 0, 0, 0.07)","0 2px 2px rgba(0, 0, 0, 0.06)"],"lg":["0 10px 8px rgba(0, 0, 0, 0.04)","0 4px 3px rgba(0, 0, 0, 0.1)"],"xl":["0 20px 13px rgba(0, 0, 0, 0.03)","0 8px 5px rgba(0, 0, 0, 0.08)"],"2xl":"0 25px 25px rgba(0, 0, 0, 0.15)","none":"0 0 #0000"},"fill":{"current":"currentColor"},"grayscale":{"0":"0","DEFAULT":"100%"},"hueRotate":{"0":"0deg","15":"15deg","30":"30deg","60":"60deg","90":"90deg","180":"180deg","-180":"-180deg","-90":"-90deg","-60":"-60deg","-30":"-30deg","-15":"-15deg"},"invert":{"0":"0","DEFAULT":"100%"},"flex":{"1":"1 1 0%","auto":"1 1 auto","initial":"0 1 auto","none":"none"},"flexGrow":{"0":"0","DEFAULT":"1"},"flexShrink":{"0":"0","DEFAULT":"1"},"fontFamily":{"sans":["ui-sans-serif","system-ui","-apple-system","BlinkMacSystemFont","\"Segoe UI\"","Roboto","\"Helvetica Neue\"","Arial","\"Noto Sans\"","sans-serif","\"Apple Color Emoji\"","\"Segoe UI Emoji\"","\"Segoe UI Symbol\"","\"Noto Color Emoji\""],"serif":["ui-serif","Georgia","Cambria","\"Times New Roman\"","Times","serif"],"mono":["ui-monospace","SFMono-Regular","Menlo","Monaco","Consolas","\"Liberation Mono\"","\"Courier New\"","monospace"]},"fontWeight":{"thin":"100","extralight":"200","light":"300","normal":"400","medium":"500","semibold":"600","bold":"700","extrabold":"800","black":"900"},"gap":{"0":"0px","1":"1px","2":"2px","4":"4px","6":"6px","8":"8px","10":"10px","12":"12px","14":"14px","16":"16px","18":"18px","20":"20px","24":"24px","28":"28px","32":"32px","40":"40px","60":"60px","80":"80px"},"gradientColorStops":{"transparent":"transparent","current":"currentColor","blue":{"from":"#8A78FD","to":"#796BFD","light":"#7084ff","DEFAULT":"#796BFD","purple":"#5F75FF"},"black":"#707280","green":"#27C193","white":"#fff","yellow":"#F29C1B","orange":"#FFB020","pink":"#F24822","red":{"light":"#F24822","DEFAULT":"#AF160E","forbidden":"#EC5151"},"gray":{"bg2":"#F5F6FA","bg":"#F5F6FA","divider":"#E5E9EF","comment":"#B4BDCC","content":"#707280","subTitle":"#4B4D59","title":"#13141A","light":"#707880","common":"#666666"},"r":{"blue-default":"var(--r-blue-default, #7084ff)","blue-light1":"var(--r-blue-light1, #eef1ff)","blue-light-1":"var(--r-blue-light-1, #eef1ff)","blue-light2":"var(--r-blue-light2, #dee3fc)","blue-light-2":"var(--r-blue-light-2, #dee3fc)","blue-disable":"var(--r-blue-disable, #dbe0ff)","green-default":"var(--r-green-default, #2abb7f)","green-light":"var(--r-green-light, #d8f2e7)","orange-default":"var(--r-orange-default, #ffb020)","orange-light":"var(--r-orange-light, #fff5e2)","red-default":"var(--r-red-default, #e34935)","red-light":"var(--r-red-light, #fff2f0)","red-dark":"var(--r-red-dark, #ae2a19)","red-light2":"var(--r-red-light2, #efd4d1)","red-light-2":"var(--r-red-light-2, #efd4d1)","neutral-title1":"var(--r-neutral-title1, #192945)","neutral-title-1":"var(--r-neutral-title-1, #192945)","neutral-body":"var(--r-neutral-body, #3e495e)","neutral-foot":"var(--r-neutral-foot, #6a7587)","neutral-line":"var(--r-neutral-line, #d3d8e0)","neutral-bg1":"var(--r-neutral-bg1, #ffffff)","neutral-bg-1":"var(--r-neutral-bg-1, #ffffff)","neutral-bg2":"var(--r-neutral-bg2, #f2f4f7)","neutral-bg-2":"var(--r-neutral-bg-2, #f2f4f7)","neutral-bg3":"var(--r-neutral-bg3, #f7fafc)","neutral-bg-3":"var(--r-neutral-bg-3, #f7fafc)","neutral-card1":"var(--r-neutral-card1, #ffffff)","neutral-card-1":"var(--r-neutral-card-1, #ffffff)","neutral-card2":"var(--r-neutral-card2, #f2f4f7)","neutral-card-2":"var(--r-neutral-card-2, #f2f4f7)","neutral-card3":"var(--r-neutral-card3, #f7fafc)","neutral-card-3":"var(--r-neutral-card-3, #f7fafc)","neutral-title2":"var(--r-neutral-title2, #ffffff)","neutral-title-2":"var(--r-neutral-title-2, #ffffff)","neutral-black":"var(--r-neutral-black, #000000)"},"rabby":{"blue-default":"var(--r-blue-default, #7084ff)","blue-light1":"var(--r-blue-light1, #eef1ff)","blue-light-1":"var(--r-blue-light-1, #eef1ff)","blue-light2":"var(--r-blue-light2, #dee3fc)","blue-light-2":"var(--r-blue-light-2, #dee3fc)","blue-disable":"var(--r-blue-disable, #dbe0ff)","green-default":"var(--r-green-default, #2abb7f)","green-light":"var(--r-green-light, #d8f2e7)","orange-default":"var(--r-orange-default, #ffb020)","orange-light":"var(--r-orange-light, #fff5e2)","red-default":"var(--r-red-default, #e34935)","red-light":"var(--r-red-light, #fff2f0)","red-dark":"var(--r-red-dark, #ae2a19)","red-light2":"var(--r-red-light2, #efd4d1)","red-light-2":"var(--r-red-light-2, #efd4d1)","neutral-title1":"var(--r-neutral-title1, #192945)","neutral-title-1":"var(--r-neutral-title-1, #192945)","neutral-body":"var(--r-neutral-body, #3e495e)","neutral-foot":"var(--r-neutral-foot, #6a7587)","neutral-line":"var(--r-neutral-line, #d3d8e0)","neutral-bg1":"var(--r-neutral-bg1, #ffffff)","neutral-bg-1":"var(--r-neutral-bg-1, #ffffff)","neutral-bg2":"var(--r-neutral-bg2, #f2f4f7)","neutral-bg-2":"var(--r-neutral-bg-2, #f2f4f7)","neutral-bg3":"var(--r-neutral-bg3, #f7fafc)","neutral-bg-3":"var(--r-neutral-bg-3, #f7fafc)","neutral-card1":"var(--r-neutral-card1, #ffffff)","neutral-card-1":"var(--r-neutral-card-1, #ffffff)","neutral-card2":"var(--r-neutral-card2, #f2f4f7)","neutral-card-2":"var(--r-neutral-card-2, #f2f4f7)","neutral-card3":"var(--r-neutral-card3, #f7fafc)","neutral-card-3":"var(--r-neutral-card-3, #f7fafc)","neutral-title2":"var(--r-neutral-title2, #ffffff)","neutral-title-2":"var(--r-neutral-title-2, #ffffff)","neutral-black":"var(--r-neutral-black, #000000)"},"-r":{"blue-default":"var(--r-blue-default, #7084ff)","blue-light1":"var(--r-blue-light1, #eef1ff)","blue-light-1":"var(--r-blue-light-1, #eef1ff)","blue-light2":"var(--r-blue-light2, #dee3fc)","blue-light-2":"var(--r-blue-light-2, #dee3fc)","blue-disable":"var(--r-blue-disable, #dbe0ff)","green-default":"var(--r-green-default, #2abb7f)","green-light":"var(--r-green-light, #d8f2e7)","orange-default":"var(--r-orange-default, #ffb020)","orange-light":"var(--r-orange-light, #fff5e2)","red-default":"var(--r-red-default, #e34935)","red-light":"var(--r-red-light, #fff2f0)","red-dark":"var(--r-red-dark, #ae2a19)","red-light2":"var(--r-red-light2, #efd4d1)","red-light-2":"var(--r-red-light-2, #efd4d1)","neutral-title1":"var(--r-neutral-title1, #192945)","neutral-title-1":"var(--r-neutral-title-1, #192945)","neutral-body":"var(--r-neutral-body, #3e495e)","neutral-foot":"var(--r-neutral-foot, #6a7587)","neutral-line":"var(--r-neutral-line, #d3d8e0)","neutral-bg1":"var(--r-neutral-bg1, #ffffff)","neutral-bg-1":"var(--r-neutral-bg-1, #ffffff)","neutral-bg2":"var(--r-neutral-bg2, #f2f4f7)","neutral-bg-2":"var(--r-neutral-bg-2, #f2f4f7)","neutral-bg3":"var(--r-neutral-bg3, #f7fafc)","neutral-bg-3":"var(--r-neutral-bg-3, #f7fafc)","neutral-card1":"var(--r-neutral-card1, #ffffff)","neutral-card-1":"var(--r-neutral-card-1, #ffffff)","neutral-card2":"var(--r-neutral-card2, #f2f4f7)","neutral-card-2":"var(--r-neutral-card-2, #f2f4f7)","neutral-card3":"var(--r-neutral-card3, #f7fafc)","neutral-card-3":"var(--r-neutral-card-3, #f7fafc)","neutral-title2":"var(--r-neutral-title2, #ffffff)","neutral-title-2":"var(--r-neutral-title-2, #ffffff)","neutral-black":"var(--r-neutral-black, #000000)"},"light-r":{"blue-default":"#7084ff","blue-light1":"#eef1ff","blue-light-1":"#eef1ff","blue-light2":"#dee3fc","blue-light-2":"#dee3fc","blue-disable":"#dbe0ff","green-default":"#2abb7f","green-light":"#d8f2e7","orange-default":"#ffb020","orange-light":"#fff5e2","red-default":"#e34935","red-light":"#fff2f0","red-dark":"#ae2a19","red-light2":"#efd4d1","red-light-2":"#efd4d1","neutral-title1":"#192945","neutral-title-1":"#192945","neutral-body":"#3e495e","neutral-foot":"#6a7587","neutral-line":"#d3d8e0","neutral-bg1":"#ffffff","neutral-bg-1":"#ffffff","neutral-bg2":"#f2f4f7","neutral-bg-2":"#f2f4f7","neutral-bg3":"#f7fafc","neutral-bg-3":"#f7fafc","neutral-card1":"#ffffff","neutral-card-1":"#ffffff","neutral-card2":"#f2f4f7","neutral-card-2":"#f2f4f7","neutral-card3":"#f7fafc","neutral-card-3":"#f7fafc","neutral-title2":"#ffffff","neutral-title-2":"#ffffff","neutral-black":"#000000"},"dark-r":{"blue-default":"#7084ff","blue-light1":"#424962","blue-light-1":"#424962","blue-light2":"#424962","blue-light-2":"#424962","blue-disable":"#4c5685","green-default":"#2abb7f","green-light":"#395a5a","orange-default":"#ffc64a","orange-light":"#484339","red-default":"#ef5c48","red-light":"#4f3a42","red-dark":"#ae2a19","red-light2":"#4f3a42","red-light-2":"#4f3a42","neutral-title1":"#f7fafc","neutral-title-1":"#f7fafc","neutral-body":"#d3d8e0","neutral-foot":"#babec5","neutral-line":"#ffffff1a","neutral-bg1":"#1c1f2b","neutral-bg-1":"#1c1f2b","neutral-bg2":"#1c1f2b","neutral-bg-2":"#1c1f2b","neutral-bg3":"#1c1f2b","neutral-bg-3":"#1c1f2b","neutral-card1":"#ffffff0f","neutral-card-1":"#ffffff0f","neutral-card2":"#ffffff0f","neutral-card-2":"#ffffff0f","neutral-card3":"#ffffff0f","neutral-card-3":"#ffffff0f","neutral-title2":"#ffffff","neutral-title-2":"#ffffff","neutral-black":"#000000"}},"gridAutoColumns":{"auto":"auto","min":"min-content","max":"max-content","fr":"minmax(0, 1fr)"},"gridAutoRows":{"auto":"auto","min":"min-content","max":"max-content","fr":"minmax(0, 1fr)"},"gridColumn":{"auto":"auto","span-1":"span 1 / span 1","span-2":"span 2 / span 2","span-3":"span 3 / span 3","span-4":"span 4 / span 4","span-5":"span 5 / span 5","span-6":"span 6 / span 6","span-7":"span 7 / span 7","span-8":"span 8 / span 8","span-9":"span 9 / span 9","span-10":"span 10 / span 10","span-11":"span 11 / span 11","span-12":"span 12 / span 12","span-full":"1 / -1"},"gridColumnEnd":{"1":"1","2":"2","3":"3","4":"4","5":"5","6":"6","7":"7","8":"8","9":"9","10":"10","11":"11","12":"12","13":"13","auto":"auto"},"gridColumnStart":{"1":"1","2":"2","3":"3","4":"4","5":"5","6":"6","7":"7","8":"8","9":"9","10":"10","11":"11","12":"12","13":"13","auto":"auto"},"gridRow":{"auto":"auto","span-1":"span 1 / span 1","span-2":"span 2 / span 2","span-3":"span 3 / span 3","span-4":"span 4 / span 4","span-5":"span 5 / span 5","span-6":"span 6 / span 6","span-full":"1 / -1"},"gridRowStart":{"1":"1","2":"2","3":"3","4":"4","5":"5","6":"6","7":"7","auto":"auto"},"gridRowEnd":{"1":"1","2":"2","3":"3","4":"4","5":"5","6":"6","7":"7","auto":"auto"},"gridTemplateColumns":{"1":"repeat(1, minmax(0, 1fr))","2":"repeat(2, minmax(0, 1fr))","3":"repeat(3, minmax(0, 1fr))","4":"repeat(4, minmax(0, 1fr))","5":"repeat(5, minmax(0, 1fr))","6":"repeat(6, minmax(0, 1fr))","7":"repeat(7, minmax(0, 1fr))","8":"repeat(8, minmax(0, 1fr))","9":"repeat(9, minmax(0, 1fr))","10":"repeat(10, minmax(0, 1fr))","11":"repeat(11, minmax(0, 1fr))","12":"repeat(12, minmax(0, 1fr))","none":"none"},"gridTemplateRows":{"1":"repeat(1, minmax(0, 1fr))","2":"repeat(2, minmax(0, 1fr))","3":"repeat(3, minmax(0, 1fr))","4":"repeat(4, minmax(0, 1fr))","5":"repeat(5, minmax(0, 1fr))","6":"repeat(6, minmax(0, 1fr))","none":"none"},"height":{"0":"0px","1":"1px","2":"2px","4":"4px","6":"6px","8":"8px","10":"10px","12":"12px","14":"14px","16":"16px","18":"18px","20":"20px","24":"24px","28":"28px","32":"32px","40":"40px","60":"60px","80":"80px","auto":"auto","1/2":"50%","1/3":"33.333333%","2/3":"66.666667%","1/4":"25%","2/4":"50%","3/4":"75%","1/5":"20%","2/5":"40%","3/5":"60%","4/5":"80%","1/6":"16.666667%","2/6":"33.333333%","3/6":"50%","4/6":"66.666667%","5/6":"83.333333%","full":"100%","screen":"100vh"},"inset":{"0":"0px","1":"1px","2":"2px","4":"4px","6":"6px","8":"8px","10":"10px","12":"12px","14":"14px","16":"16px","18":"18px","20":"20px","24":"24px","28":"28px","32":"32px","40":"40px","60":"60px","80":"80px","auto":"auto","-0":"0px","-1":"-1px","-2":"-2px","-4":"-4px","-6":"-6px","-8":"-8px","-10":"-10px","-12":"-12px","-14":"-14px","-16":"-16px","-18":"-18px","-20":"-20px","-24":"-24px","-28":"-28px","-32":"-32px","-40":"-40px","-60":"-60px","-80":"-80px","1/2":"50%","1/3":"33.333333%","2/3":"66.666667%","1/4":"25%","2/4":"50%","3/4":"75%","full":"100%","-1/2":"-50%","-1/3":"-33.333333%","-2/3":"-66.666667%","-1/4":"-25%","-2/4":"-50%","-3/4":"-75%","-full":"-100%"},"keyframes":{"spin":{"to":{"transform":"rotate(360deg)"}},"ping":{"75%, 100%":{"transform":"scale(2)","opacity":"0"}},"pulse":{"50%":{"opacity":".5"}},"bounce":{"0%, 100%":{"transform":"translateY(-25%)","animationTimingFunction":"cubic-bezier(0.8,0,1,1)"},"50%":{"transform":"none","animationTimingFunction":"cubic-bezier(0,0,0.2,1)"}}},"letterSpacing":{"tighter":"-0.05em","tight":"-0.025em","normal":"0em","wide":"0.025em","wider":"0.05em","widest":"0.1em"},"lineHeight":{"3":".75rem","4":"1rem","5":"1.25rem","6":"1.5rem","7":"1.75rem","8":"2rem","9":"2.25rem","10":"2.5rem","none":"1","tight":"1.25","snug":"1.375","normal":"1.5","relaxed":"1.625","loose":"2"},"listStyleType":{"none":"none","disc":"disc","decimal":"decimal"},"margin":{"0":"0px","1":"1px","2":"2px","4":"4px","6":"6px","8":"8px","10":"10px","12":"12px","14":"14px","16":"16px","18":"18px","20":"20px","24":"24px","28":"28px","32":"32px","40":"40px","60":"60px","80":"80px","auto":"auto","-0":"0px","-1":"-1px","-2":"-2px","-4":"-4px","-6":"-6px","-8":"-8px","-10":"-10px","-12":"-12px","-14":"-14px","-16":"-16px","-18":"-18px","-20":"-20px","-24":"-24px","-28":"-28px","-32":"-32px","-40":"-40px","-60":"-60px","-80":"-80px"},"maxHeight":{"0":"0px","1":"1px","2":"2px","4":"4px","6":"6px","8":"8px","10":"10px","12":"12px","14":"14px","16":"16px","18":"18px","20":"20px","24":"24px","28":"28px","32":"32px","40":"40px","60":"60px","80":"80px","full":"100%","screen":"100vh"},"maxWidth":{"0":"0rem","none":"none","xs":"20rem","sm":"24rem","md":"28rem","lg":"32rem","xl":"36rem","2xl":"42rem","3xl":"48rem","4xl":"56rem","5xl":"64rem","6xl":"72rem","7xl":"80rem","full":"100%","min":"min-content","max":"max-content","prose":"65ch"},"minHeight":{"0":"0px","full":"100%","screen":"100vh"},"minWidth":{"0":"0px","full":"100%","min":"min-content","max":"max-content"},"objectPosition":{"bottom":"bottom","center":"center","left":"left","left-bottom":"left bottom","left-top":"left top","right":"right","right-bottom":"right bottom","right-top":"right top","top":"top"},"opacity":{"0":"0","5":"0.05","10":"0.1","20":"0.2","25":"0.25","30":"0.3","40":"0.4","50":"0.5","60":"0.6","70":"0.7","75":"0.75","80":"0.8","90":"0.9","95":"0.95","100":"1"},"order":{"1":"1","2":"2","3":"3","4":"4","5":"5","6":"6","7":"7","8":"8","9":"9","10":"10","11":"11","12":"12","first":"-9999","last":"9999","none":"0"},"outline":{"none":["2px solid transparent","2px"],"white":["2px dotted white","2px"],"black":["2px dotted black","2px"]},"padding":{"0":"0px","1":"1px","2":"2px","4":"4px","6":"6px","8":"8px","10":"10px","12":"12px","14":"14px","16":"16px","18":"18px","20":"20px","24":"24px","28":"28px","32":"32px","40":"40px","60":"60px","80":"80px"},"placeholderColor":{"transparent":"transparent","current":"currentColor","blue":{"from":"#8A78FD","to":"#796BFD","light":"#7084ff","DEFAULT":"#796BFD","purple":"#5F75FF"},"black":"#707280","green":"#27C193","white":"#fff","yellow":"#F29C1B","orange":"#FFB020","pink":"#F24822","red":{"light":"#F24822","DEFAULT":"#AF160E","forbidden":"#EC5151"},"gray":{"bg2":"#F5F6FA","bg":"#F5F6FA","divider":"#E5E9EF","comment":"#B4BDCC","content":"#707280","subTitle":"#4B4D59","title":"#13141A","light":"#707880","common":"#666666"},"r":{"blue-default":"var(--r-blue-default, #7084ff)","blue-light1":"var(--r-blue-light1, #eef1ff)","blue-light-1":"var(--r-blue-light-1, #eef1ff)","blue-light2":"var(--r-blue-light2, #dee3fc)","blue-light-2":"var(--r-blue-light-2, #dee3fc)","blue-disable":"var(--r-blue-disable, #dbe0ff)","green-default":"var(--r-green-default, #2abb7f)","green-light":"var(--r-green-light, #d8f2e7)","orange-default":"var(--r-orange-default, #ffb020)","orange-light":"var(--r-orange-light, #fff5e2)","red-default":"var(--r-red-default, #e34935)","red-light":"var(--r-red-light, #fff2f0)","red-dark":"var(--r-red-dark, #ae2a19)","red-light2":"var(--r-red-light2, #efd4d1)","red-light-2":"var(--r-red-light-2, #efd4d1)","neutral-title1":"var(--r-neutral-title1, #192945)","neutral-title-1":"var(--r-neutral-title-1, #192945)","neutral-body":"var(--r-neutral-body, #3e495e)","neutral-foot":"var(--r-neutral-foot, #6a7587)","neutral-line":"var(--r-neutral-line, #d3d8e0)","neutral-bg1":"var(--r-neutral-bg1, #ffffff)","neutral-bg-1":"var(--r-neutral-bg-1, #ffffff)","neutral-bg2":"var(--r-neutral-bg2, #f2f4f7)","neutral-bg-2":"var(--r-neutral-bg-2, #f2f4f7)","neutral-bg3":"var(--r-neutral-bg3, #f7fafc)","neutral-bg-3":"var(--r-neutral-bg-3, #f7fafc)","neutral-card1":"var(--r-neutral-card1, #ffffff)","neutral-card-1":"var(--r-neutral-card-1, #ffffff)","neutral-card2":"var(--r-neutral-card2, #f2f4f7)","neutral-card-2":"var(--r-neutral-card-2, #f2f4f7)","neutral-card3":"var(--r-neutral-card3, #f7fafc)","neutral-card-3":"var(--r-neutral-card-3, #f7fafc)","neutral-title2":"var(--r-neutral-title2, #ffffff)","neutral-title-2":"var(--r-neutral-title-2, #ffffff)","neutral-black":"var(--r-neutral-black, #000000)"},"rabby":{"blue-default":"var(--r-blue-default, #7084ff)","blue-light1":"var(--r-blue-light1, #eef1ff)","blue-light-1":"var(--r-blue-light-1, #eef1ff)","blue-light2":"var(--r-blue-light2, #dee3fc)","blue-light-2":"var(--r-blue-light-2, #dee3fc)","blue-disable":"var(--r-blue-disable, #dbe0ff)","green-default":"var(--r-green-default, #2abb7f)","green-light":"var(--r-green-light, #d8f2e7)","orange-default":"var(--r-orange-default, #ffb020)","orange-light":"var(--r-orange-light, #fff5e2)","red-default":"var(--r-red-default, #e34935)","red-light":"var(--r-red-light, #fff2f0)","red-dark":"var(--r-red-dark, #ae2a19)","red-light2":"var(--r-red-light2, #efd4d1)","red-light-2":"var(--r-red-light-2, #efd4d1)","neutral-title1":"var(--r-neutral-title1, #192945)","neutral-title-1":"var(--r-neutral-title-1, #192945)","neutral-body":"var(--r-neutral-body, #3e495e)","neutral-foot":"var(--r-neutral-foot, #6a7587)","neutral-line":"var(--r-neutral-line, #d3d8e0)","neutral-bg1":"var(--r-neutral-bg1, #ffffff)","neutral-bg-1":"var(--r-neutral-bg-1, #ffffff)","neutral-bg2":"var(--r-neutral-bg2, #f2f4f7)","neutral-bg-2":"var(--r-neutral-bg-2, #f2f4f7)","neutral-bg3":"var(--r-neutral-bg3, #f7fafc)","neutral-bg-3":"var(--r-neutral-bg-3, #f7fafc)","neutral-card1":"var(--r-neutral-card1, #ffffff)","neutral-card-1":"var(--r-neutral-card-1, #ffffff)","neutral-card2":"var(--r-neutral-card2, #f2f4f7)","neutral-card-2":"var(--r-neutral-card-2, #f2f4f7)","neutral-card3":"var(--r-neutral-card3, #f7fafc)","neutral-card-3":"var(--r-neutral-card-3, #f7fafc)","neutral-title2":"var(--r-neutral-title2, #ffffff)","neutral-title-2":"var(--r-neutral-title-2, #ffffff)","neutral-black":"var(--r-neutral-black, #000000)"},"-r":{"blue-default":"var(--r-blue-default, #7084ff)","blue-light1":"var(--r-blue-light1, #eef1ff)","blue-light-1":"var(--r-blue-light-1, #eef1ff)","blue-light2":"var(--r-blue-light2, #dee3fc)","blue-light-2":"var(--r-blue-light-2, #dee3fc)","blue-disable":"var(--r-blue-disable, #dbe0ff)","green-default":"var(--r-green-default, #2abb7f)","green-light":"var(--r-green-light, #d8f2e7)","orange-default":"var(--r-orange-default, #ffb020)","orange-light":"var(--r-orange-light, #fff5e2)","red-default":"var(--r-red-default, #e34935)","red-light":"var(--r-red-light, #fff2f0)","red-dark":"var(--r-red-dark, #ae2a19)","red-light2":"var(--r-red-light2, #efd4d1)","red-light-2":"var(--r-red-light-2, #efd4d1)","neutral-title1":"var(--r-neutral-title1, #192945)","neutral-title-1":"var(--r-neutral-title-1, #192945)","neutral-body":"var(--r-neutral-body, #3e495e)","neutral-foot":"var(--r-neutral-foot, #6a7587)","neutral-line":"var(--r-neutral-line, #d3d8e0)","neutral-bg1":"var(--r-neutral-bg1, #ffffff)","neutral-bg-1":"var(--r-neutral-bg-1, #ffffff)","neutral-bg2":"var(--r-neutral-bg2, #f2f4f7)","neutral-bg-2":"var(--r-neutral-bg-2, #f2f4f7)","neutral-bg3":"var(--r-neutral-bg3, #f7fafc)","neutral-bg-3":"var(--r-neutral-bg-3, #f7fafc)","neutral-card1":"var(--r-neutral-card1, #ffffff)","neutral-card-1":"var(--r-neutral-card-1, #ffffff)","neutral-card2":"var(--r-neutral-card2, #f2f4f7)","neutral-card-2":"var(--r-neutral-card-2, #f2f4f7)","neutral-card3":"var(--r-neutral-card3, #f7fafc)","neutral-card-3":"var(--r-neutral-card-3, #f7fafc)","neutral-title2":"var(--r-neutral-title2, #ffffff)","neutral-title-2":"var(--r-neutral-title-2, #ffffff)","neutral-black":"var(--r-neutral-black, #000000)"},"light-r":{"blue-default":"#7084ff","blue-light1":"#eef1ff","blue-light-1":"#eef1ff","blue-light2":"#dee3fc","blue-light-2":"#dee3fc","blue-disable":"#dbe0ff","green-default":"#2abb7f","green-light":"#d8f2e7","orange-default":"#ffb020","orange-light":"#fff5e2","red-default":"#e34935","red-light":"#fff2f0","red-dark":"#ae2a19","red-light2":"#efd4d1","red-light-2":"#efd4d1","neutral-title1":"#192945","neutral-title-1":"#192945","neutral-body":"#3e495e","neutral-foot":"#6a7587","neutral-line":"#d3d8e0","neutral-bg1":"#ffffff","neutral-bg-1":"#ffffff","neutral-bg2":"#f2f4f7","neutral-bg-2":"#f2f4f7","neutral-bg3":"#f7fafc","neutral-bg-3":"#f7fafc","neutral-card1":"#ffffff","neutral-card-1":"#ffffff","neutral-card2":"#f2f4f7","neutral-card-2":"#f2f4f7","neutral-card3":"#f7fafc","neutral-card-3":"#f7fafc","neutral-title2":"#ffffff","neutral-title-2":"#ffffff","neutral-black":"#000000"},"dark-r":{"blue-default":"#7084ff","blue-light1":"#424962","blue-light-1":"#424962","blue-light2":"#424962","blue-light-2":"#424962","blue-disable":"#4c5685","green-default":"#2abb7f","green-light":"#395a5a","orange-default":"#ffc64a","orange-light":"#484339","red-default":"#ef5c48","red-light":"#4f3a42","red-dark":"#ae2a19","red-light2":"#4f3a42","red-light-2":"#4f3a42","neutral-title1":"#f7fafc","neutral-title-1":"#f7fafc","neutral-body":"#d3d8e0","neutral-foot":"#babec5","neutral-line":"#ffffff1a","neutral-bg1":"#1c1f2b","neutral-bg-1":"#1c1f2b","neutral-bg2":"#1c1f2b","neutral-bg-2":"#1c1f2b","neutral-bg3":"#1c1f2b","neutral-bg-3":"#1c1f2b","neutral-card1":"#ffffff0f","neutral-card-1":"#ffffff0f","neutral-card2":"#ffffff0f","neutral-card-2":"#ffffff0f","neutral-card3":"#ffffff0f","neutral-card-3":"#ffffff0f","neutral-title2":"#ffffff","neutral-title-2":"#ffffff","neutral-black":"#000000"}},"placeholderOpacity":{"0":"0","5":"0.05","10":"0.1","20":"0.2","25":"0.25","30":"0.3","40":"0.4","50":"0.5","60":"0.6","70":"0.7","75":"0.75","80":"0.8","90":"0.9","95":"0.95","100":"1"},"ringColor":{"DEFAULT":"#3b82f6","transparent":"transparent","current":"currentColor","blue":{"from":"#8A78FD","to":"#796BFD","light":"#7084ff","DEFAULT":"#796BFD","purple":"#5F75FF"},"black":"#707280","green":"#27C193","white":"#fff","yellow":"#F29C1B","orange":"#FFB020","pink":"#F24822","red":{"light":"#F24822","DEFAULT":"#AF160E","forbidden":"#EC5151"},"gray":{"bg2":"#F5F6FA","bg":"#F5F6FA","divider":"#E5E9EF","comment":"#B4BDCC","content":"#707280","subTitle":"#4B4D59","title":"#13141A","light":"#707880","common":"#666666"},"r":{"blue-default":"var(--r-blue-default, #7084ff)","blue-light1":"var(--r-blue-light1, #eef1ff)","blue-light-1":"var(--r-blue-light-1, #eef1ff)","blue-light2":"var(--r-blue-light2, #dee3fc)","blue-light-2":"var(--r-blue-light-2, #dee3fc)","blue-disable":"var(--r-blue-disable, #dbe0ff)","green-default":"var(--r-green-default, #2abb7f)","green-light":"var(--r-green-light, #d8f2e7)","orange-default":"var(--r-orange-default, #ffb020)","orange-light":"var(--r-orange-light, #fff5e2)","red-default":"var(--r-red-default, #e34935)","red-light":"var(--r-red-light, #fff2f0)","red-dark":"var(--r-red-dark, #ae2a19)","red-light2":"var(--r-red-light2, #efd4d1)","red-light-2":"var(--r-red-light-2, #efd4d1)","neutral-title1":"var(--r-neutral-title1, #192945)","neutral-title-1":"var(--r-neutral-title-1, #192945)","neutral-body":"var(--r-neutral-body, #3e495e)","neutral-foot":"var(--r-neutral-foot, #6a7587)","neutral-line":"var(--r-neutral-line, #d3d8e0)","neutral-bg1":"var(--r-neutral-bg1, #ffffff)","neutral-bg-1":"var(--r-neutral-bg-1, #ffffff)","neutral-bg2":"var(--r-neutral-bg2, #f2f4f7)","neutral-bg-2":"var(--r-neutral-bg-2, #f2f4f7)","neutral-bg3":"var(--r-neutral-bg3, #f7fafc)","neutral-bg-3":"var(--r-neutral-bg-3, #f7fafc)","neutral-card1":"var(--r-neutral-card1, #ffffff)","neutral-card-1":"var(--r-neutral-card-1, #ffffff)","neutral-card2":"var(--r-neutral-card2, #f2f4f7)","neutral-card-2":"var(--r-neutral-card-2, #f2f4f7)","neutral-card3":"var(--r-neutral-card3, #f7fafc)","neutral-card-3":"var(--r-neutral-card-3, #f7fafc)","neutral-title2":"var(--r-neutral-title2, #ffffff)","neutral-title-2":"var(--r-neutral-title-2, #ffffff)","neutral-black":"var(--r-neutral-black, #000000)"},"rabby":{"blue-default":"var(--r-blue-default, #7084ff)","blue-light1":"var(--r-blue-light1, #eef1ff)","blue-light-1":"var(--r-blue-light-1, #eef1ff)","blue-light2":"var(--r-blue-light2, #dee3fc)","blue-light-2":"var(--r-blue-light-2, #dee3fc)","blue-disable":"var(--r-blue-disable, #dbe0ff)","green-default":"var(--r-green-default, #2abb7f)","green-light":"var(--r-green-light, #d8f2e7)","orange-default":"var(--r-orange-default, #ffb020)","orange-light":"var(--r-orange-light, #fff5e2)","red-default":"var(--r-red-default, #e34935)","red-light":"var(--r-red-light, #fff2f0)","red-dark":"var(--r-red-dark, #ae2a19)","red-light2":"var(--r-red-light2, #efd4d1)","red-light-2":"var(--r-red-light-2, #efd4d1)","neutral-title1":"var(--r-neutral-title1, #192945)","neutral-title-1":"var(--r-neutral-title-1, #192945)","neutral-body":"var(--r-neutral-body, #3e495e)","neutral-foot":"var(--r-neutral-foot, #6a7587)","neutral-line":"var(--r-neutral-line, #d3d8e0)","neutral-bg1":"var(--r-neutral-bg1, #ffffff)","neutral-bg-1":"var(--r-neutral-bg-1, #ffffff)","neutral-bg2":"var(--r-neutral-bg2, #f2f4f7)","neutral-bg-2":"var(--r-neutral-bg-2, #f2f4f7)","neutral-bg3":"var(--r-neutral-bg3, #f7fafc)","neutral-bg-3":"var(--r-neutral-bg-3, #f7fafc)","neutral-card1":"var(--r-neutral-card1, #ffffff)","neutral-card-1":"var(--r-neutral-card-1, #ffffff)","neutral-card2":"var(--r-neutral-card2, #f2f4f7)","neutral-card-2":"var(--r-neutral-card-2, #f2f4f7)","neutral-card3":"var(--r-neutral-card3, #f7fafc)","neutral-card-3":"var(--r-neutral-card-3, #f7fafc)","neutral-title2":"var(--r-neutral-title2, #ffffff)","neutral-title-2":"var(--r-neutral-title-2, #ffffff)","neutral-black":"var(--r-neutral-black, #000000)"},"-r":{"blue-default":"var(--r-blue-default, #7084ff)","blue-light1":"var(--r-blue-light1, #eef1ff)","blue-light-1":"var(--r-blue-light-1, #eef1ff)","blue-light2":"var(--r-blue-light2, #dee3fc)","blue-light-2":"var(--r-blue-light-2, #dee3fc)","blue-disable":"var(--r-blue-disable, #dbe0ff)","green-default":"var(--r-green-default, #2abb7f)","green-light":"var(--r-green-light, #d8f2e7)","orange-default":"var(--r-orange-default, #ffb020)","orange-light":"var(--r-orange-light, #fff5e2)","red-default":"var(--r-red-default, #e34935)","red-light":"var(--r-red-light, #fff2f0)","red-dark":"var(--r-red-dark, #ae2a19)","red-light2":"var(--r-red-light2, #efd4d1)","red-light-2":"var(--r-red-light-2, #efd4d1)","neutral-title1":"var(--r-neutral-title1, #192945)","neutral-title-1":"var(--r-neutral-title-1, #192945)","neutral-body":"var(--r-neutral-body, #3e495e)","neutral-foot":"var(--r-neutral-foot, #6a7587)","neutral-line":"var(--r-neutral-line, #d3d8e0)","neutral-bg1":"var(--r-neutral-bg1, #ffffff)","neutral-bg-1":"var(--r-neutral-bg-1, #ffffff)","neutral-bg2":"var(--r-neutral-bg2, #f2f4f7)","neutral-bg-2":"var(--r-neutral-bg-2, #f2f4f7)","neutral-bg3":"var(--r-neutral-bg3, #f7fafc)","neutral-bg-3":"var(--r-neutral-bg-3, #f7fafc)","neutral-card1":"var(--r-neutral-card1, #ffffff)","neutral-card-1":"var(--r-neutral-card-1, #ffffff)","neutral-card2":"var(--r-neutral-card2, #f2f4f7)","neutral-card-2":"var(--r-neutral-card-2, #f2f4f7)","neutral-card3":"var(--r-neutral-card3, #f7fafc)","neutral-card-3":"var(--r-neutral-card-3, #f7fafc)","neutral-title2":"var(--r-neutral-title2, #ffffff)","neutral-title-2":"var(--r-neutral-title-2, #ffffff)","neutral-black":"var(--r-neutral-black, #000000)"},"light-r":{"blue-default":"#7084ff","blue-light1":"#eef1ff","blue-light-1":"#eef1ff","blue-light2":"#dee3fc","blue-light-2":"#dee3fc","blue-disable":"#dbe0ff","green-default":"#2abb7f","green-light":"#d8f2e7","orange-default":"#ffb020","orange-light":"#fff5e2","red-default":"#e34935","red-light":"#fff2f0","red-dark":"#ae2a19","red-light2":"#efd4d1","red-light-2":"#efd4d1","neutral-title1":"#192945","neutral-title-1":"#192945","neutral-body":"#3e495e","neutral-foot":"#6a7587","neutral-line":"#d3d8e0","neutral-bg1":"#ffffff","neutral-bg-1":"#ffffff","neutral-bg2":"#f2f4f7","neutral-bg-2":"#f2f4f7","neutral-bg3":"#f7fafc","neutral-bg-3":"#f7fafc","neutral-card1":"#ffffff","neutral-card-1":"#ffffff","neutral-card2":"#f2f4f7","neutral-card-2":"#f2f4f7","neutral-card3":"#f7fafc","neutral-card-3":"#f7fafc","neutral-title2":"#ffffff","neutral-title-2":"#ffffff","neutral-black":"#000000"},"dark-r":{"blue-default":"#7084ff","blue-light1":"#424962","blue-light-1":"#424962","blue-light2":"#424962","blue-light-2":"#424962","blue-disable":"#4c5685","green-default":"#2abb7f","green-light":"#395a5a","orange-default":"#ffc64a","orange-light":"#484339","red-default":"#ef5c48","red-light":"#4f3a42","red-dark":"#ae2a19","red-light2":"#4f3a42","red-light-2":"#4f3a42","neutral-title1":"#f7fafc","neutral-title-1":"#f7fafc","neutral-body":"#d3d8e0","neutral-foot":"#babec5","neutral-line":"#ffffff1a","neutral-bg1":"#1c1f2b","neutral-bg-1":"#1c1f2b","neutral-bg2":"#1c1f2b","neutral-bg-2":"#1c1f2b","neutral-bg3":"#1c1f2b","neutral-bg-3":"#1c1f2b","neutral-card1":"#ffffff0f","neutral-card-1":"#ffffff0f","neutral-card2":"#ffffff0f","neutral-card-2":"#ffffff0f","neutral-card3":"#ffffff0f","neutral-card-3":"#ffffff0f","neutral-title2":"#ffffff","neutral-title-2":"#ffffff","neutral-black":"#000000"}},"ringOffsetColor":{"transparent":"transparent","current":"currentColor","blue":{"from":"#8A78FD","to":"#796BFD","light":"#7084ff","DEFAULT":"#796BFD","purple":"#5F75FF"},"black":"#707280","green":"#27C193","white":"#fff","yellow":"#F29C1B","orange":"#FFB020","pink":"#F24822","red":{"light":"#F24822","DEFAULT":"#AF160E","forbidden":"#EC5151"},"gray":{"bg2":"#F5F6FA","bg":"#F5F6FA","divider":"#E5E9EF","comment":"#B4BDCC","content":"#707280","subTitle":"#4B4D59","title":"#13141A","light":"#707880","common":"#666666"},"r":{"blue-default":"var(--r-blue-default, #7084ff)","blue-light1":"var(--r-blue-light1, #eef1ff)","blue-light-1":"var(--r-blue-light-1, #eef1ff)","blue-light2":"var(--r-blue-light2, #dee3fc)","blue-light-2":"var(--r-blue-light-2, #dee3fc)","blue-disable":"var(--r-blue-disable, #dbe0ff)","green-default":"var(--r-green-default, #2abb7f)","green-light":"var(--r-green-light, #d8f2e7)","orange-default":"var(--r-orange-default, #ffb020)","orange-light":"var(--r-orange-light, #fff5e2)","red-default":"var(--r-red-default, #e34935)","red-light":"var(--r-red-light, #fff2f0)","red-dark":"var(--r-red-dark, #ae2a19)","red-light2":"var(--r-red-light2, #efd4d1)","red-light-2":"var(--r-red-light-2, #efd4d1)","neutral-title1":"var(--r-neutral-title1, #192945)","neutral-title-1":"var(--r-neutral-title-1, #192945)","neutral-body":"var(--r-neutral-body, #3e495e)","neutral-foot":"var(--r-neutral-foot, #6a7587)","neutral-line":"var(--r-neutral-line, #d3d8e0)","neutral-bg1":"var(--r-neutral-bg1, #ffffff)","neutral-bg-1":"var(--r-neutral-bg-1, #ffffff)","neutral-bg2":"var(--r-neutral-bg2, #f2f4f7)","neutral-bg-2":"var(--r-neutral-bg-2, #f2f4f7)","neutral-bg3":"var(--r-neutral-bg3, #f7fafc)","neutral-bg-3":"var(--r-neutral-bg-3, #f7fafc)","neutral-card1":"var(--r-neutral-card1, #ffffff)","neutral-card-1":"var(--r-neutral-card-1, #ffffff)","neutral-card2":"var(--r-neutral-card2, #f2f4f7)","neutral-card-2":"var(--r-neutral-card-2, #f2f4f7)","neutral-card3":"var(--r-neutral-card3, #f7fafc)","neutral-card-3":"var(--r-neutral-card-3, #f7fafc)","neutral-title2":"var(--r-neutral-title2, #ffffff)","neutral-title-2":"var(--r-neutral-title-2, #ffffff)","neutral-black":"var(--r-neutral-black, #000000)"},"rabby":{"blue-default":"var(--r-blue-default, #7084ff)","blue-light1":"var(--r-blue-light1, #eef1ff)","blue-light-1":"var(--r-blue-light-1, #eef1ff)","blue-light2":"var(--r-blue-light2, #dee3fc)","blue-light-2":"var(--r-blue-light-2, #dee3fc)","blue-disable":"var(--r-blue-disable, #dbe0ff)","green-default":"var(--r-green-default, #2abb7f)","green-light":"var(--r-green-light, #d8f2e7)","orange-default":"var(--r-orange-default, #ffb020)","orange-light":"var(--r-orange-light, #fff5e2)","red-default":"var(--r-red-default, #e34935)","red-light":"var(--r-red-light, #fff2f0)","red-dark":"var(--r-red-dark, #ae2a19)","red-light2":"var(--r-red-light2, #efd4d1)","red-light-2":"var(--r-red-light-2, #efd4d1)","neutral-title1":"var(--r-neutral-title1, #192945)","neutral-title-1":"var(--r-neutral-title-1, #192945)","neutral-body":"var(--r-neutral-body, #3e495e)","neutral-foot":"var(--r-neutral-foot, #6a7587)","neutral-line":"var(--r-neutral-line, #d3d8e0)","neutral-bg1":"var(--r-neutral-bg1, #ffffff)","neutral-bg-1":"var(--r-neutral-bg-1, #ffffff)","neutral-bg2":"var(--r-neutral-bg2, #f2f4f7)","neutral-bg-2":"var(--r-neutral-bg-2, #f2f4f7)","neutral-bg3":"var(--r-neutral-bg3, #f7fafc)","neutral-bg-3":"var(--r-neutral-bg-3, #f7fafc)","neutral-card1":"var(--r-neutral-card1, #ffffff)","neutral-card-1":"var(--r-neutral-card-1, #ffffff)","neutral-card2":"var(--r-neutral-card2, #f2f4f7)","neutral-card-2":"var(--r-neutral-card-2, #f2f4f7)","neutral-card3":"var(--r-neutral-card3, #f7fafc)","neutral-card-3":"var(--r-neutral-card-3, #f7fafc)","neutral-title2":"var(--r-neutral-title2, #ffffff)","neutral-title-2":"var(--r-neutral-title-2, #ffffff)","neutral-black":"var(--r-neutral-black, #000000)"},"-r":{"blue-default":"var(--r-blue-default, #7084ff)","blue-light1":"var(--r-blue-light1, #eef1ff)","blue-light-1":"var(--r-blue-light-1, #eef1ff)","blue-light2":"var(--r-blue-light2, #dee3fc)","blue-light-2":"var(--r-blue-light-2, #dee3fc)","blue-disable":"var(--r-blue-disable, #dbe0ff)","green-default":"var(--r-green-default, #2abb7f)","green-light":"var(--r-green-light, #d8f2e7)","orange-default":"var(--r-orange-default, #ffb020)","orange-light":"var(--r-orange-light, #fff5e2)","red-default":"var(--r-red-default, #e34935)","red-light":"var(--r-red-light, #fff2f0)","red-dark":"var(--r-red-dark, #ae2a19)","red-light2":"var(--r-red-light2, #efd4d1)","red-light-2":"var(--r-red-light-2, #efd4d1)","neutral-title1":"var(--r-neutral-title1, #192945)","neutral-title-1":"var(--r-neutral-title-1, #192945)","neutral-body":"var(--r-neutral-body, #3e495e)","neutral-foot":"var(--r-neutral-foot, #6a7587)","neutral-line":"var(--r-neutral-line, #d3d8e0)","neutral-bg1":"var(--r-neutral-bg1, #ffffff)","neutral-bg-1":"var(--r-neutral-bg-1, #ffffff)","neutral-bg2":"var(--r-neutral-bg2, #f2f4f7)","neutral-bg-2":"var(--r-neutral-bg-2, #f2f4f7)","neutral-bg3":"var(--r-neutral-bg3, #f7fafc)","neutral-bg-3":"var(--r-neutral-bg-3, #f7fafc)","neutral-card1":"var(--r-neutral-card1, #ffffff)","neutral-card-1":"var(--r-neutral-card-1, #ffffff)","neutral-card2":"var(--r-neutral-card2, #f2f4f7)","neutral-card-2":"var(--r-neutral-card-2, #f2f4f7)","neutral-card3":"var(--r-neutral-card3, #f7fafc)","neutral-card-3":"var(--r-neutral-card-3, #f7fafc)","neutral-title2":"var(--r-neutral-title2, #ffffff)","neutral-title-2":"var(--r-neutral-title-2, #ffffff)","neutral-black":"var(--r-neutral-black, #000000)"},"light-r":{"blue-default":"#7084ff","blue-light1":"#eef1ff","blue-light-1":"#eef1ff","blue-light2":"#dee3fc","blue-light-2":"#dee3fc","blue-disable":"#dbe0ff","green-default":"#2abb7f","green-light":"#d8f2e7","orange-default":"#ffb020","orange-light":"#fff5e2","red-default":"#e34935","red-light":"#fff2f0","red-dark":"#ae2a19","red-light2":"#efd4d1","red-light-2":"#efd4d1","neutral-title1":"#192945","neutral-title-1":"#192945","neutral-body":"#3e495e","neutral-foot":"#6a7587","neutral-line":"#d3d8e0","neutral-bg1":"#ffffff","neutral-bg-1":"#ffffff","neutral-bg2":"#f2f4f7","neutral-bg-2":"#f2f4f7","neutral-bg3":"#f7fafc","neutral-bg-3":"#f7fafc","neutral-card1":"#ffffff","neutral-card-1":"#ffffff","neutral-card2":"#f2f4f7","neutral-card-2":"#f2f4f7","neutral-card3":"#f7fafc","neutral-card-3":"#f7fafc","neutral-title2":"#ffffff","neutral-title-2":"#ffffff","neutral-black":"#000000"},"dark-r":{"blue-default":"#7084ff","blue-light1":"#424962","blue-light-1":"#424962","blue-light2":"#424962","blue-light-2":"#424962","blue-disable":"#4c5685","green-default":"#2abb7f","green-light":"#395a5a","orange-default":"#ffc64a","orange-light":"#484339","red-default":"#ef5c48","red-light":"#4f3a42","red-dark":"#ae2a19","red-light2":"#4f3a42","red-light-2":"#4f3a42","neutral-title1":"#f7fafc","neutral-title-1":"#f7fafc","neutral-body":"#d3d8e0","neutral-foot":"#babec5","neutral-line":"#ffffff1a","neutral-bg1":"#1c1f2b","neutral-bg-1":"#1c1f2b","neutral-bg2":"#1c1f2b","neutral-bg-2":"#1c1f2b","neutral-bg3":"#1c1f2b","neutral-bg-3":"#1c1f2b","neutral-card1":"#ffffff0f","neutral-card-1":"#ffffff0f","neutral-card2":"#ffffff0f","neutral-card-2":"#ffffff0f","neutral-card3":"#ffffff0f","neutral-card-3":"#ffffff0f","neutral-title2":"#ffffff","neutral-title-2":"#ffffff","neutral-black":"#000000"}},"ringOffsetWidth":{"0":"0px","1":"1px","2":"2px","4":"4px","8":"8px"},"ringOpacity":{"0":"0","5":"0.05","10":"0.1","20":"0.2","25":"0.25","30":"0.3","40":"0.4","50":"0.5","60":"0.6","70":"0.7","75":"0.75","80":"0.8","90":"0.9","95":"0.95","100":"1","DEFAULT":"0.5"},"ringWidth":{"0":"0px","1":"1px","2":"2px","4":"4px","8":"8px","DEFAULT":"3px"},"rotate":{"0":"0deg","1":"1deg","2":"2deg","3":"3deg","6":"6deg","12":"12deg","45":"45deg","90":"90deg","180":"180deg","-180":"-180deg","-90":"-90deg","-45":"-45deg","-12":"-12deg","-6":"-6deg","-3":"-3deg","-2":"-2deg","-1":"-1deg"},"saturate":{"0":"0","50":".5","100":"1","150":"1.5","200":"2"},"scale":{"0":"0","50":".5","75":".75","90":".9","95":".95","100":"1","105":"1.05","110":"1.1","125":"1.25","150":"1.5"},"sepia":{"0":"0","DEFAULT":"100%"},"skew":{"0":"0deg","1":"1deg","2":"2deg","3":"3deg","6":"6deg","12":"12deg","-12":"-12deg","-6":"-6deg","-3":"-3deg","-2":"-2deg","-1":"-1deg"},"space":{"0":"0px","1":"1px","2":"2px","4":"4px","6":"6px","8":"8px","10":"10px","12":"12px","14":"14px","16":"16px","18":"18px","20":"20px","24":"24px","28":"28px","32":"32px","40":"40px","60":"60px","80":"80px","-0":"0px","-1":"-1px","-2":"-2px","-4":"-4px","-6":"-6px","-8":"-8px","-10":"-10px","-12":"-12px","-14":"-14px","-16":"-16px","-18":"-18px","-20":"-20px","-24":"-24px","-28":"-28px","-32":"-32px","-40":"-40px","-60":"-60px","-80":"-80px"},"stroke":{"current":"currentColor"},"strokeWidth":{"0":"0","1":"1","2":"2"},"textColor":{"transparent":"transparent","current":"currentColor","blue":{"from":"#8A78FD","to":"#796BFD","light":"#7084ff","DEFAULT":"#796BFD","purple":"#5F75FF"},"black":"#707280","green":"#27C193","white":"#fff","yellow":"#F29C1B","orange":"#FFB020","pink":"#F24822","red":{"light":"#F24822","DEFAULT":"#AF160E","forbidden":"#EC5151"},"gray":{"bg2":"#F5F6FA","bg":"#F5F6FA","divider":"#E5E9EF","comment":"#B4BDCC","content":"#707280","subTitle":"#4B4D59","title":"#13141A","light":"#707880","common":"#666666"},"r":{"blue-default":"var(--r-blue-default, #7084ff)","blue-light1":"var(--r-blue-light1, #eef1ff)","blue-light-1":"var(--r-blue-light-1, #eef1ff)","blue-light2":"var(--r-blue-light2, #dee3fc)","blue-light-2":"var(--r-blue-light-2, #dee3fc)","blue-disable":"var(--r-blue-disable, #dbe0ff)","green-default":"var(--r-green-default, #2abb7f)","green-light":"var(--r-green-light, #d8f2e7)","orange-default":"var(--r-orange-default, #ffb020)","orange-light":"var(--r-orange-light, #fff5e2)","red-default":"var(--r-red-default, #e34935)","red-light":"var(--r-red-light, #fff2f0)","red-dark":"var(--r-red-dark, #ae2a19)","red-light2":"var(--r-red-light2, #efd4d1)","red-light-2":"var(--r-red-light-2, #efd4d1)","neutral-title1":"var(--r-neutral-title1, #192945)","neutral-title-1":"var(--r-neutral-title-1, #192945)","neutral-body":"var(--r-neutral-body, #3e495e)","neutral-foot":"var(--r-neutral-foot, #6a7587)","neutral-line":"var(--r-neutral-line, #d3d8e0)","neutral-bg1":"var(--r-neutral-bg1, #ffffff)","neutral-bg-1":"var(--r-neutral-bg-1, #ffffff)","neutral-bg2":"var(--r-neutral-bg2, #f2f4f7)","neutral-bg-2":"var(--r-neutral-bg-2, #f2f4f7)","neutral-bg3":"var(--r-neutral-bg3, #f7fafc)","neutral-bg-3":"var(--r-neutral-bg-3, #f7fafc)","neutral-card1":"var(--r-neutral-card1, #ffffff)","neutral-card-1":"var(--r-neutral-card-1, #ffffff)","neutral-card2":"var(--r-neutral-card2, #f2f4f7)","neutral-card-2":"var(--r-neutral-card-2, #f2f4f7)","neutral-card3":"var(--r-neutral-card3, #f7fafc)","neutral-card-3":"var(--r-neutral-card-3, #f7fafc)","neutral-title2":"var(--r-neutral-title2, #ffffff)","neutral-title-2":"var(--r-neutral-title-2, #ffffff)","neutral-black":"var(--r-neutral-black, #000000)"},"rabby":{"blue-default":"var(--r-blue-default, #7084ff)","blue-light1":"var(--r-blue-light1, #eef1ff)","blue-light-1":"var(--r-blue-light-1, #eef1ff)","blue-light2":"var(--r-blue-light2, #dee3fc)","blue-light-2":"var(--r-blue-light-2, #dee3fc)","blue-disable":"var(--r-blue-disable, #dbe0ff)","green-default":"var(--r-green-default, #2abb7f)","green-light":"var(--r-green-light, #d8f2e7)","orange-default":"var(--r-orange-default, #ffb020)","orange-light":"var(--r-orange-light, #fff5e2)","red-default":"var(--r-red-default, #e34935)","red-light":"var(--r-red-light, #fff2f0)","red-dark":"var(--r-red-dark, #ae2a19)","red-light2":"var(--r-red-light2, #efd4d1)","red-light-2":"var(--r-red-light-2, #efd4d1)","neutral-title1":"var(--r-neutral-title1, #192945)","neutral-title-1":"var(--r-neutral-title-1, #192945)","neutral-body":"var(--r-neutral-body, #3e495e)","neutral-foot":"var(--r-neutral-foot, #6a7587)","neutral-line":"var(--r-neutral-line, #d3d8e0)","neutral-bg1":"var(--r-neutral-bg1, #ffffff)","neutral-bg-1":"var(--r-neutral-bg-1, #ffffff)","neutral-bg2":"var(--r-neutral-bg2, #f2f4f7)","neutral-bg-2":"var(--r-neutral-bg-2, #f2f4f7)","neutral-bg3":"var(--r-neutral-bg3, #f7fafc)","neutral-bg-3":"var(--r-neutral-bg-3, #f7fafc)","neutral-card1":"var(--r-neutral-card1, #ffffff)","neutral-card-1":"var(--r-neutral-card-1, #ffffff)","neutral-card2":"var(--r-neutral-card2, #f2f4f7)","neutral-card-2":"var(--r-neutral-card-2, #f2f4f7)","neutral-card3":"var(--r-neutral-card3, #f7fafc)","neutral-card-3":"var(--r-neutral-card-3, #f7fafc)","neutral-title2":"var(--r-neutral-title2, #ffffff)","neutral-title-2":"var(--r-neutral-title-2, #ffffff)","neutral-black":"var(--r-neutral-black, #000000)"},"-r":{"blue-default":"var(--r-blue-default, #7084ff)","blue-light1":"var(--r-blue-light1, #eef1ff)","blue-light-1":"var(--r-blue-light-1, #eef1ff)","blue-light2":"var(--r-blue-light2, #dee3fc)","blue-light-2":"var(--r-blue-light-2, #dee3fc)","blue-disable":"var(--r-blue-disable, #dbe0ff)","green-default":"var(--r-green-default, #2abb7f)","green-light":"var(--r-green-light, #d8f2e7)","orange-default":"var(--r-orange-default, #ffb020)","orange-light":"var(--r-orange-light, #fff5e2)","red-default":"var(--r-red-default, #e34935)","red-light":"var(--r-red-light, #fff2f0)","red-dark":"var(--r-red-dark, #ae2a19)","red-light2":"var(--r-red-light2, #efd4d1)","red-light-2":"var(--r-red-light-2, #efd4d1)","neutral-title1":"var(--r-neutral-title1, #192945)","neutral-title-1":"var(--r-neutral-title-1, #192945)","neutral-body":"var(--r-neutral-body, #3e495e)","neutral-foot":"var(--r-neutral-foot, #6a7587)","neutral-line":"var(--r-neutral-line, #d3d8e0)","neutral-bg1":"var(--r-neutral-bg1, #ffffff)","neutral-bg-1":"var(--r-neutral-bg-1, #ffffff)","neutral-bg2":"var(--r-neutral-bg2, #f2f4f7)","neutral-bg-2":"var(--r-neutral-bg-2, #f2f4f7)","neutral-bg3":"var(--r-neutral-bg3, #f7fafc)","neutral-bg-3":"var(--r-neutral-bg-3, #f7fafc)","neutral-card1":"var(--r-neutral-card1, #ffffff)","neutral-card-1":"var(--r-neutral-card-1, #ffffff)","neutral-card2":"var(--r-neutral-card2, #f2f4f7)","neutral-card-2":"var(--r-neutral-card-2, #f2f4f7)","neutral-card3":"var(--r-neutral-card3, #f7fafc)","neutral-card-3":"var(--r-neutral-card-3, #f7fafc)","neutral-title2":"var(--r-neutral-title2, #ffffff)","neutral-title-2":"var(--r-neutral-title-2, #ffffff)","neutral-black":"var(--r-neutral-black, #000000)"},"light-r":{"blue-default":"#7084ff","blue-light1":"#eef1ff","blue-light-1":"#eef1ff","blue-light2":"#dee3fc","blue-light-2":"#dee3fc","blue-disable":"#dbe0ff","green-default":"#2abb7f","green-light":"#d8f2e7","orange-default":"#ffb020","orange-light":"#fff5e2","red-default":"#e34935","red-light":"#fff2f0","red-dark":"#ae2a19","red-light2":"#efd4d1","red-light-2":"#efd4d1","neutral-title1":"#192945","neutral-title-1":"#192945","neutral-body":"#3e495e","neutral-foot":"#6a7587","neutral-line":"#d3d8e0","neutral-bg1":"#ffffff","neutral-bg-1":"#ffffff","neutral-bg2":"#f2f4f7","neutral-bg-2":"#f2f4f7","neutral-bg3":"#f7fafc","neutral-bg-3":"#f7fafc","neutral-card1":"#ffffff","neutral-card-1":"#ffffff","neutral-card2":"#f2f4f7","neutral-card-2":"#f2f4f7","neutral-card3":"#f7fafc","neutral-card-3":"#f7fafc","neutral-title2":"#ffffff","neutral-title-2":"#ffffff","neutral-black":"#000000"},"dark-r":{"blue-default":"#7084ff","blue-light1":"#424962","blue-light-1":"#424962","blue-light2":"#424962","blue-light-2":"#424962","blue-disable":"#4c5685","green-default":"#2abb7f","green-light":"#395a5a","orange-default":"#ffc64a","orange-light":"#484339","red-default":"#ef5c48","red-light":"#4f3a42","red-dark":"#ae2a19","red-light2":"#4f3a42","red-light-2":"#4f3a42","neutral-title1":"#f7fafc","neutral-title-1":"#f7fafc","neutral-body":"#d3d8e0","neutral-foot":"#babec5","neutral-line":"#ffffff1a","neutral-bg1":"#1c1f2b","neutral-bg-1":"#1c1f2b","neutral-bg2":"#1c1f2b","neutral-bg-2":"#1c1f2b","neutral-bg3":"#1c1f2b","neutral-bg-3":"#1c1f2b","neutral-card1":"#ffffff0f","neutral-card-1":"#ffffff0f","neutral-card2":"#ffffff0f","neutral-card-2":"#ffffff0f","neutral-card3":"#ffffff0f","neutral-card-3":"#ffffff0f","neutral-title2":"#ffffff","neutral-title-2":"#ffffff","neutral-black":"#000000"}},"textOpacity":{"0":"0","5":"0.05","10":"0.1","20":"0.2","25":"0.25","30":"0.3","40":"0.4","50":"0.5","60":"0.6","70":"0.7","75":"0.75","80":"0.8","90":"0.9","95":"0.95","100":"1"},"transformOrigin":{"center":"center","top":"top","top-right":"top right","right":"right","bottom-right":"bottom right","bottom":"bottom","bottom-left":"bottom left","left":"left","top-left":"top left"},"transitionDelay":{"75":"75ms","100":"100ms","150":"150ms","200":"200ms","300":"300ms","500":"500ms","700":"700ms","1000":"1000ms"},"transitionDuration":{"75":"75ms","100":"100ms","150":"150ms","200":"200ms","300":"300ms","500":"500ms","700":"700ms","1000":"1000ms","DEFAULT":"150ms"},"transitionProperty":{"none":"none","all":"all","DEFAULT":"background-color, border-color, color, fill, stroke, opacity, box-shadow, transform, filter, backdrop-filter","colors":"background-color, border-color, color, fill, stroke","opacity":"opacity","shadow":"box-shadow","transform":"transform"},"transitionTimingFunction":{"DEFAULT":"cubic-bezier(0.4, 0, 0.2, 1)","linear":"linear","in":"cubic-bezier(0.4, 0, 1, 1)","out":"cubic-bezier(0, 0, 0.2, 1)","in-out":"cubic-bezier(0.4, 0, 0.2, 1)"},"translate":{"0":"0px","1":"1px","2":"2px","4":"4px","6":"6px","8":"8px","10":"10px","12":"12px","14":"14px","16":"16px","18":"18px","20":"20px","24":"24px","28":"28px","32":"32px","40":"40px","60":"60px","80":"80px","-0":"0px","-1":"-1px","-2":"-2px","-4":"-4px","-6":"-6px","-8":"-8px","-10":"-10px","-12":"-12px","-14":"-14px","-16":"-16px","-18":"-18px","-20":"-20px","-24":"-24px","-28":"-28px","-32":"-32px","-40":"-40px","-60":"-60px","-80":"-80px","1/2":"50%","1/3":"33.333333%","2/3":"66.666667%","1/4":"25%","2/4":"50%","3/4":"75%","full":"100%","-1/2":"-50%","-1/3":"-33.333333%","-2/3":"-66.666667%","-1/4":"-25%","-2/4":"-50%","-3/4":"-75%","-full":"-100%"},"width":{"0":"0px","1":"1px","2":"2px","4":"4px","6":"6px","8":"8px","10":"10px","12":"12px","14":"14px","16":"16px","18":"18px","20":"20px","24":"24px","28":"28px","32":"32px","40":"40px","60":"60px","80":"80px","auto":"auto","1/2":"50%","1/3":"33.333333%","2/3":"66.666667%","1/4":"25%","2/4":"50%","3/4":"75%","1/5":"20%","2/5":"40%","3/5":"60%","4/5":"80%","1/6":"16.666667%","2/6":"33.333333%","3/6":"50%","4/6":"66.666667%","5/6":"83.333333%","1/12":"8.333333%","2/12":"16.666667%","3/12":"25%","4/12":"33.333333%","5/12":"41.666667%","6/12":"50%","7/12":"58.333333%","8/12":"66.666667%","9/12":"75%","10/12":"83.333333%","11/12":"91.666667%","full":"100%","screen":"100vw","min":"min-content","max":"max-content"},"zIndex":{"0":"0","10":"10","20":"20","30":"30","40":"40","50":"50","auto":"auto"}},"variants":{"accessibility":["responsive","focus-within","focus"],"alignContent":["responsive"],"alignItems":["responsive"],"alignSelf":["responsive"],"animation":["responsive"],"appearance":["responsive"],"backdropBlur":["responsive"],"backdropBrightness":["responsive"],"backdropContrast":["responsive"],"backdropDropShadow":["responsive"],"backdropFilter":["responsive"],"backdropGrayscale":["responsive"],"backdropHueRotate":["responsive"],"backdropInvert":["responsive"],"backdropSaturate":["responsive"],"backdropSepia":["responsive"],"backgroundAttachment":["responsive"],"backgroundBlendMode":["responsive"],"backgroundClip":["responsive"],"backgroundColor":["responsive","dark","group-hover","focus-within","hover","focus"],"backgroundImage":["responsive"],"backgroundOpacity":["responsive","dark","group-hover","focus-within","hover","focus"],"backgroundPosition":["responsive"],"backgroundRepeat":["responsive"],"backgroundSize":["responsive"],"backgroundOrigin":["responsive"],"blur":["responsive"],"borderCollapse":["responsive"],"borderColor":["responsive","dark","group-hover","focus-within","hover","focus"],"borderOpacity":["responsive","dark","group-hover","focus-within","hover","focus"],"borderRadius":["responsive"],"borderStyle":["responsive"],"borderWidth":["responsive"],"boxDecorationBreak":["responsive"],"boxShadow":["responsive","group-hover","focus-within","hover","focus"],"boxSizing":["responsive"],"brightness":["responsive"],"clear":["responsive"],"container":["responsive"],"contrast":["responsive"],"cursor":["responsive"],"display":["responsive"],"divideColor":["responsive","dark"],"divideOpacity":["responsive","dark"],"divideStyle":["responsive"],"divideWidth":["responsive"],"dropShadow":["responsive"],"fill":["responsive"],"filter":["responsive"],"flex":["responsive"],"flexDirection":["responsive"],"flexGrow":["responsive"],"flexShrink":["responsive"],"flexWrap":["responsive"],"float":["responsive"],"fontFamily":["responsive"],"fontSize":["responsive"],"fontSmoothing":["responsive"],"fontStyle":["responsive"],"fontVariantNumeric":["responsive"],"fontWeight":["responsive"],"gap":["responsive"],"gradientColorStops":["responsive","dark","hover","focus"],"grayscale":["responsive"],"gridAutoColumns":["responsive"],"gridAutoFlow":["responsive"],"gridAutoRows":["responsive"],"gridColumn":["responsive"],"gridColumnEnd":["responsive"],"gridColumnStart":["responsive"],"gridRow":["responsive"],"gridRowEnd":["responsive"],"gridRowStart":["responsive"],"gridTemplateColumns":["responsive"],"gridTemplateRows":["responsive"],"height":["responsive"],"hueRotate":["responsive"],"inset":["responsive"],"invert":["responsive"],"isolation":["responsive"],"justifyContent":["responsive"],"justifyItems":["responsive"],"justifySelf":["responsive"],"letterSpacing":["responsive"],"lineHeight":["responsive"],"listStylePosition":["responsive"],"listStyleType":["responsive"],"margin":["responsive"],"maxHeight":["responsive"],"maxWidth":["responsive"],"minHeight":["responsive"],"minWidth":["responsive"],"mixBlendMode":["responsive"],"objectFit":["responsive"],"objectPosition":["responsive"],"opacity":["responsive","group-hover","focus-within","hover","focus"],"order":["responsive"],"outline":["responsive","focus-within","focus"],"overflow":["responsive"],"overscrollBehavior":["responsive"],"padding":["responsive"],"placeContent":["responsive"],"placeItems":["responsive"],"placeSelf":["responsive"],"placeholderColor":["responsive","dark","focus"],"placeholderOpacity":["responsive","dark","focus"],"pointerEvents":["responsive"],"position":["responsive"],"resize":["responsive"],"ringColor":["responsive","dark","focus-within","focus"],"ringOffsetColor":["responsive","dark","focus-within","focus"],"ringOffsetWidth":["responsive","focus-within","focus"],"ringOpacity":["responsive","dark","focus-within","focus"],"ringWidth":["responsive","focus-within","focus"],"rotate":["responsive","hover","focus"],"saturate":["responsive"],"scale":["responsive","hover","focus"],"sepia":["responsive"],"skew":["responsive","hover","focus"],"space":["responsive"],"stroke":["responsive"],"strokeWidth":["responsive"],"tableLayout":["responsive"],"textAlign":["responsive"],"textColor":["responsive","dark","group-hover","focus-within","hover","focus"],"textDecoration":["responsive","group-hover","focus-within","hover","focus"],"textOpacity":["responsive","dark","group-hover","focus-within","hover","focus"],"textOverflow":["responsive"],"textTransform":["responsive"],"transform":["responsive"],"transformOrigin":["responsive"],"transitionDelay":["responsive"],"transitionDuration":["responsive"],"transitionProperty":["responsive"],"transitionTimingFunction":["responsive"],"translate":["responsive","hover","focus"],"userSelect":["responsive"],"verticalAlign":["responsive"],"visibility":["responsive"],"whitespace":["responsive"],"width":["responsive"],"wordBreak":["responsive"],"zIndex":["responsive","focus-within","focus"]},"corePlugins":["preflight","container","accessibility","pointerEvents","visibility","position","inset","isolation","zIndex","order","gridColumn","gridColumnStart","gridColumnEnd","gridRow","gridRowStart","gridRowEnd","float","clear","margin","boxSizing","display","height","maxHeight","minHeight","width","minWidth","maxWidth","flex","flexShrink","flexGrow","tableLayout","borderCollapse","transformOrigin","translate","rotate","skew","scale","transform","animation","cursor","userSelect","resize","listStylePosition","listStyleType","appearance","gridAutoColumns","gridAutoFlow","gridAutoRows","gridTemplateColumns","gridTemplateRows","flexDirection","flexWrap","placeContent","placeItems","alignContent","alignItems","justifyContent","justifyItems","gap","space","divideWidth","divideStyle","divideColor","divideOpacity","placeSelf","alignSelf","justifySelf","overflow","overscrollBehavior","textOverflow","whitespace","wordBreak","borderRadius","borderWidth","borderStyle","borderColor","borderOpacity","backgroundColor","backgroundOpacity","backgroundImage","gradientColorStops","boxDecorationBreak","backgroundSize","backgroundAttachment","backgroundClip","backgroundPosition","backgroundRepeat","backgroundOrigin","fill","stroke","strokeWidth","objectFit","objectPosition","padding","textAlign","verticalAlign","fontFamily","fontSize","fontWeight","textTransform","fontStyle","fontVariantNumeric","lineHeight","letterSpacing","textColor","textOpacity","textDecoration","fontSmoothing","placeholderColor","placeholderOpacity","caretColor","opacity","backgroundBlendMode","mixBlendMode","boxShadow","outline","ringWidth","ringColor","ringOpacity","ringOffsetWidth","ringOffsetColor","blur","brightness","contrast","dropShadow","grayscale","hueRotate","invert","saturate","sepia","filter","backdropBlur","backdropBrightness","backdropContrast","backdropGrayscale","backdropHueRotate","backdropInvert","backdropOpacity","backdropSaturate","backdropSepia","backdropFilter","transitionProperty","transitionDelay","transitionDuration","transitionTimingFunction","content"],"mode":"jit","purge":["./src/ui/**/*.{ts,tsx,html}"],"darkMode":"class","important":true,"presets":[],"variantOrder":["first","last","odd","even","visited","checked","empty","read-only","group-hover","group-focus","focus-within","hover","focus","focus-visible","active","disabled"],"prefix":"","separator":":"}}